{
  "totalFields": 204,
  "byPage": [
    {
      "page": "1",
      "count": 49
    },
    {
      "page": "2",
      "count": 37
    },
    {
      "page": "3",
      "count": 51
    },
    {
      "page": "4",
      "count": 46
    },
    {
      "page": "5",
      "count": 17
    },
    {
      "page": "unknown",
      "count": 4
    }
  ],
  "categorized": [
    {
      "category": "caseInfo",
      "count": 6,
      "fields": [
        {
          "name": "CM-110[0].Page1[0].P1Caption[0].captionSub[0].CaseNumber[0].caseNumber[0]",
          "description": "Case number",
          "type": "Text"
        },
        {
          "name": "CM-110[0].Page2[0].PxCaption[0].CaseNumber[0].caseNumber[0]",
          "description": "Case number",
          "type": "Text"
        },
        {
          "name": "CM-110[0].Page2[0].List9[0].item9[0].casew[0]",
          "description": "Additional representation is described in Attachment 8.",
          "type": "Button"
        },
        {
          "name": "CM-110[0].Page3[0].PxCaption[0].CaseNumber[0].caseNumber[0]",
          "description": "Case number",
          "type": "Text"
        },
        {
          "name": "CM-110[0].Page4[0].PxCaption[0].CaseNumber[0].caseNumber[0]",
          "description": "Case number",
          "type": "Text"
        },
        {
          "name": "CM-110[0].Page5[0].PxCaption[0].CaseNumber[0].caseNumber[0]",
          "description": "Case number",
          "type": "Text"
        }
      ]
    },
    {
      "category": "attorney",
      "count": 11,
      "fields": [
        {
          "name": "CM-110[0].Page1[0].P1Caption[0].AttyPartyInfo[0].AttyBarNo[0]",
          "description": "State Bar number",
          "type": "Text"
        },
        {
          "name": "CM-110[0].Page1[0].P1Caption[0].AttyPartyInfo[0].Name[0]",
          "description": "Name",
          "type": "Text"
        },
        {
          "name": "CM-110[0].Page1[0].P1Caption[0].AttyPartyInfo[0].AttyFirm[0]",
          "description": "FIrm name",
          "type": "Text"
        },
        {
          "name": "CM-110[0].Page1[0].P1Caption[0].AttyPartyInfo[0].Street[0]",
          "description": "Street address",
          "type": "Text"
        },
        {
          "name": "CM-110[0].Page1[0].P1Caption[0].AttyPartyInfo[0].City[0]",
          "description": "City",
          "type": "Text"
        },
        {
          "name": "CM-110[0].Page1[0].P1Caption[0].AttyPartyInfo[0].State[0]",
          "description": "State",
          "type": "Text"
        },
        {
          "name": "CM-110[0].Page1[0].P1Caption[0].AttyPartyInfo[0].Zip[0]",
          "description": "Zip code",
          "type": "Text"
        },
        {
          "name": "CM-110[0].Page1[0].P1Caption[0].AttyPartyInfo[0].Phone[0]",
          "description": "Telephone number:",
          "type": "Text"
        },
        {
          "name": "CM-110[0].Page1[0].P1Caption[0].AttyPartyInfo[0].Fax[0]",
          "description": "Fax number:",
          "type": "Text"
        },
        {
          "name": "CM-110[0].Page1[0].P1Caption[0].AttyPartyInfo[0].Email[0]",
          "description": "Email address",
          "type": "Text"
        },
        {
          "name": "CM-110[0].Page1[0].P1Caption[0].AttyPartyInfo[0].AttyFor[0]",
          "description": "Attorney for (name)",
          "type": "Text"
        }
      ]
    },
    {
      "category": "plaintiff",
      "count": 6,
      "fields": [
        {
          "name": "CM-110[0].Page1[0].P1Caption[0].TitlePartyName[0].Party1[0]",
          "description": "PLAINTIFF or PETITIONER:",
          "type": "Text"
        },
        {
          "name": "CM-110[0].Page2[0].PxCaption[0].TitlePartyName[0].Party1[0]",
          "description": "PLAINTIFF or PETITIONER:",
          "type": "Text"
        },
        {
          "name": "CM-110[0].Page2[0].List10[0].Lib[0].SubListb[0].Lii2[0].CheckBox03[0]",
          "description": "Plaintiff elects to refer this case to judicial arbitration and agrees to limit recovery to the amount specified in Code of\rCivil Procedure section 1141.11.",
          "type": "Button"
        },
        {
          "name": "CM-110[0].Page3[0].PxCaption[0].TitlePartyName[0].Party1[0]",
          "description": "PLAINTIFF or PETITIONER:",
          "type": "Text"
        },
        {
          "name": "CM-110[0].Page4[0].PxCaption[0].TitlePartyName[0].Party1[0]",
          "description": "PLAINTIFF or PETITIONER:",
          "type": "Text"
        },
        {
          "name": "CM-110[0].Page5[0].PxCaption[0].TitlePartyName[0].Party1[0]",
          "description": "PLAINTIFF or PETITIONER:",
          "type": "Text"
        }
      ]
    },
    {
      "category": "defendant",
      "count": 5,
      "fields": [
        {
          "name": "CM-110[0].Page1[0].P1Caption[0].TitlePartyName[0].Party2[0]",
          "description": "DEFENDANT or RESPONDENT:",
          "type": "Text"
        },
        {
          "name": "CM-110[0].Page2[0].PxCaption[0].TitlePartyName[0].Party2[0]",
          "description": "DEFENDANT or RESPONDENT:",
          "type": "Text"
        },
        {
          "name": "CM-110[0].Page3[0].PxCaption[0].TitlePartyName[0].Party2[0]",
          "description": "DEFENDANT or RESPONDENT:",
          "type": "Text"
        },
        {
          "name": "CM-110[0].Page4[0].PxCaption[0].TitlePartyName[0].Party2[0]",
          "description": "DEFENDANT or RESPONDENT:",
          "type": "Text"
        },
        {
          "name": "CM-110[0].Page5[0].PxCaption[0].TitlePartyName[0].Party2[0]",
          "description": "DEFENDANT or RESPONDENT:",
          "type": "Text"
        }
      ]
    },
    {
      "category": "address",
      "count": 2,
      "fields": [
        {
          "name": "CM-110[0].Page1[0].P1Caption[0].CourtInfo[0].CrtCounty[0]",
          "description": "Superior Court of California, County of",
          "type": "Text"
        },
        {
          "name": "CM-110[0].Page1[0].P1Caption[0].CourtInfo[0].CrtCityZip[0]",
          "description": "City and zip code",
          "type": "Text"
        }
      ]
    },
    {
      "category": "discovery",
      "count": 0,
      "fields": []
    },
    {
      "category": "other",
      "count": 174,
      "fields": [
        {
          "name": "CM-110[0].Page1[0].P1Caption[0].CourtInfo[0].CrtStreet[0]",
          "description": "Street address",
          "type": "Text"
        },
        {
          "name": "CM-110[0].Page1[0].P1Caption[0].CourtInfo[0].CrtMailingAdd[0]",
          "description": "Mailing address",
          "type": "Text"
        },
        {
          "name": "CM-110[0].Page1[0].P1Caption[0].CourtInfo[0].CrtBranch[0]",
          "description": "Branch name",
          "type": "Text"
        },
        {
          "name": "CM-110[0].Page1[0].P1Caption[0].FormTitle[0].limit12[0]",
          "description": "UNLIMITED CASE (Amount demanded exceeds 35,000 dollar)",
          "type": "Button"
        },
        {
          "name": "CM-110[0].Page1[0].P1Caption[0].FormTitle[0].limit12[1]",
          "description": "LIMITED CASE (Amount demanded is 35,000 dollar or less)",
          "type": "Button"
        },
        {
          "name": "CM-110[0].Page1[0].Note[0].Date1[0]",
          "description": "Date",
          "type": "Text"
        },
        {
          "name": "CM-110[0].Page1[0].Note[0].Time1[0]",
          "description": "Time",
          "type": "Text"
        },
        {
          "name": "CM-110[0].Page1[0].Note[0].Dept1[0]",
          "description": "Department",
          "type": "Text"
        },
        {
          "name": "CM-110[0].Page1[0].Note[0].Div1[0]",
          "description": "Division",
          "type": "Text"
        },
        {
          "name": "CM-110[0].Page1[0].Note[0].Rm1[0]",
          "description": "Room",
          "type": "Text"
        },
        {
          "name": "CM-110[0].Page1[0].Note[0].FillText1[0]",
          "description": "Address of court (if different from the address above):",
          "type": "Text"
        },
        {
          "name": "CM-110[0].Page1[0].Note[0].Ch1[0]",
          "description": "Notice of Intent to Appear by Telephone,",
          "type": "Button"
        },
        {
          "name": "CM-110[0].Page1[0].Note[0].TextField1[0]",
          "description": "by (name):",
          "type": "Text"
        },
        {
          "name": "CM-110[0].Page1[0].List1[0].Lia[0].partystatement1[0]",
          "description": "This statement is submitted by party",
          "type": "Button"
        },
        {
          "name": "CM-110[0].Page1[0].List1[0].Lia[0].TextField2[0]",
          "description": "name",
          "type": "Text"
        },
        {
          "name": "CM-110[0].Page1[0].List1[0].Lib[0].partystatement1[0]",
          "description": "This statement is submitted jointly by parties",
          "type": "Button"
        },
        {
          "name": "CM-110[0].Page1[0].List1[0].Lib[0].TextField3[0]",
          "description": "names",
          "type": "Text"
        },
        {
          "name": "CM-110[0].Page1[0].List2[0].Lia[0].Date3[0]",
          "description": "The complaint was filed on date",
          "type": "Text"
        },
        {
          "name": "CM-110[0].Page1[0].List2[0].Lib[0].Ch3[0]",
          "description": "The cross-complaint, if any, was filed on",
          "type": "Button"
        },
        {
          "name": "CM-110[0].Page1[0].List2[0].Lib[0].Date4[0]",
          "description": "date",
          "type": "Text"
        },
        {
          "name": "CM-110[0].Page1[0].List3[0].Lia[0].limitedee[0]",
          "description": "All parties named in the complaint and cross-complaint have been served, have appeared, or have been dismissed.",
          "type": "Button"
        },
        {
          "name": "CM-110[0].Page1[0].List3[0].lib[0].Ch5[0]",
          "description": "The following parties named in the complaint or cross-complaint",
          "type": "Button"
        },
        {
          "name": "CM-110[0].Page1[0].List3[0].lib[0].sublist[0].Lii1[0].Ch6[0]",
          "description": "have not been served",
          "type": "Button"
        },
        {
          "name": "CM-110[0].Page1[0].List3[0].lib[0].sublist[0].Lii1[0].TextField4[0]",
          "description": "(specify names and explain why not):",
          "type": "Text"
        },
        {
          "name": "CM-110[0].Page1[0].List3[0].lib[0].sublist[0].Lii2[0].Ch7[0]",
          "description": "have been served but have not appeared and have not been dismissed",
          "type": "Button"
        },
        {
          "name": "CM-110[0].Page1[0].List3[0].lib[0].sublist[0].Lii2[0].TextField5[0]",
          "description": "(specify names):",
          "type": "Text"
        },
        {
          "name": "CM-110[0].Page1[0].List3[0].lib[0].sublist[0].li3[0].Ch8[0]",
          "description": "Have had a default entered against them",
          "type": "Button"
        },
        {
          "name": "CM-110[0].Page1[0].List3[0].lib[0].sublist[0].li3[0].TextField7[0]",
          "description": "specify names:",
          "type": "Text"
        },
        {
          "name": "CM-110[0].Page1[0].List3[0].Lic[0].Ch9[0]",
          "description": "The following additional parties may be added ",
          "type": "Button"
        },
        {
          "name": "CM-110[0].Page1[0].List3[0].Lic[0].TextField9[0]",
          "description": "specify names, nature of involvement in case, and date by which they may be served:",
          "type": "Text"
        },
        {
          "name": "CM-110[0].Page1[0].List4[0].Lia[0].FillText11[0]",
          "description": "Describe, including causes of action",
          "type": "Text"
        },
        {
          "name": "CM-110[0].Page1[0].List4[0].Lia[0].Ch10[0]",
          "description": "complaint",
          "type": "Button"
        },
        {
          "name": "CM-110[0].Page1[0].List4[0].Lia[0].Ch10[1]",
          "description": "cross-complaint",
          "type": "Button"
        },
        {
          "name": "CM-110[0].Page2[0].List4[0].Lib[0].FillText13[0]",
          "description": "Provide a brief statement of the case, including any damages (if personal injury damages are sought, specify the injury and\rdamages claimed, including medical expenses to date [indicate source and amount], estimated future medical expenses, lost\rearnings to date, and estimated future lost earnings; if equitable relief is sought, describe the nature of the relief):",
          "type": "Text"
        },
        {
          "name": "CM-110[0].Page2[0].List4[0].Ch15[0]",
          "description": "(If more space is needed, check this box and attach a page designated as Attachment 4b.)",
          "type": "Button"
        },
        {
          "name": "CM-110[0].Page2[0].List5[0].item5[0].FillText16[0]",
          "description": "If more than one party, provide the name of each party requesting a jury trial",
          "type": "Text"
        },
        {
          "name": "CM-110[0].Page2[0].List5[0].item5[0].jurytrial1[0]",
          "description": "a jury triaI",
          "type": "Button"
        },
        {
          "name": "CM-110[0].Page2[0].List5[0].item5[0].jurytrial1[1]",
          "description": "a nonjury trial.",
          "type": "Button"
        },
        {
          "name": "CM-110[0].Page2[0].List6[0].Lia[0].Ch20[0]",
          "description": "The trial has been set for",
          "type": "Button"
        },
        {
          "name": "CM-110[0].Page2[0].List6[0].Lia[0].Date7[0]",
          "description": "date",
          "type": "Text"
        },
        {
          "name": "CM-110[0].Page2[0].List6[0].Lib[0].Ch20[0]",
          "description": "No trial date has been set. This case will be ready for trial within 12 months of the date of the filing of the complaint.",
          "type": "Button"
        },
        {
          "name": "CM-110[0].Page2[0].List6[0].Lib[0].FillText8[0]",
          "description": "IF not, explain",
          "type": "Text"
        },
        {
          "name": "CM-110[0].Page2[0].List6[0].Lic[0].FillText12[0]",
          "description": "Dates on which parties or attorneys will not be available for trial (specify dates and explain reasons for unavailability):",
          "type": "Text"
        },
        {
          "name": "CM-110[0].Page2[0].List7[0].Lia[0].estimation1[0]",
          "description": "days",
          "type": "Button"
        },
        {
          "name": "CM-110[0].Page2[0].List7[0].Lia[0].specify[0]",
          "description": "specify number",
          "type": "Text"
        },
        {
          "name": "CM-110[0].Page2[0].List7[0].Lib[0].estimation1[0]",
          "description": "hours (short causes)",
          "type": "Button"
        },
        {
          "name": "CM-110[0].Page2[0].List7[0].Lib[0].specify2[0]",
          "description": "specify",
          "type": "Text"
        },
        {
          "name": "CM-110[0].Page2[0].List8[0].Ch25[0]",
          "description": "by the attorney or party listed in the caption",
          "type": "Button"
        },
        {
          "name": "CM-110[0].Page2[0].List8[0].Ch26[0]",
          "description": "by the following:",
          "type": "Button"
        },
        {
          "name": "CM-110[0].Page2[0].List8[0].Lia[0].FillText20[0]",
          "description": "Attorney",
          "type": "Text"
        },
        {
          "name": "CM-110[0].Page2[0].List8[0].Lib[0].FillText21[0]",
          "description": "Firm",
          "type": "Text"
        },
        {
          "name": "CM-110[0].Page2[0].List8[0].Lic[0].FillText22[0]",
          "description": "Address",
          "type": "Text"
        },
        {
          "name": "CM-110[0].Page2[0].List8[0].Lid[0].FillText23[0]",
          "description": "Telephone number",
          "type": "Text"
        },
        {
          "name": "CM-110[0].Page2[0].List8[0].Lie[0].TextField24[0]",
          "description": "EMail address",
          "type": "Text"
        },
        {
          "name": "CM-110[0].Page2[0].List8[0].Lif[0].FillText25[0]",
          "description": "Fax number",
          "type": "Text"
        },
        {
          "name": "CM-110[0].Page2[0].List8[0].Lig[0].FillText26[0]",
          "description": "Party represented",
          "type": "Text"
        },
        {
          "name": "CM-110[0].Page2[0].List8[0].att[0]",
          "description": "Additional representation is described in Attachment 8.",
          "type": "Button"
        },
        {
          "name": "CM-110[0].Page2[0].List9[0].item9[0].section[0]",
          "description": "Specify code section",
          "type": "Text"
        },
        {
          "name": "CM-110[0].Page2[0].List10[0].Lia[0].SubLista[0].Lii1[0].counsel1[0]",
          "description": "has",
          "type": "Button"
        },
        {
          "name": "CM-110[0].Page2[0].List10[0].Lia[0].SubLista[0].Lii1[0].counsel1[1]",
          "description": "has not",
          "type": "Button"
        },
        {
          "name": "CM-110[0].Page2[0].List10[0].Lia[0].SubLista[0].Lii2[0].partya1[0]",
          "description": "has",
          "type": "Button"
        },
        {
          "name": "CM-110[0].Page2[0].List10[0].Lia[0].SubLista[0].Lii2[0].partya1[1]",
          "description": "has not",
          "type": "Button"
        },
        {
          "name": "CM-110[0].Page2[0].List10[0].Lib[0].SubListb[0].Lii1[0].arbitration[0]",
          "description": "This matter is subject to mandatory judicial arbitration under Code of Civil Procedure section 1141.11 or to civil action mediation under Code of Civil Procedure section 1775.3 because the amount in controversy does not exceed the statutory limit.",
          "type": "Button"
        },
        {
          "name": "CM-110[0].Page2[0].List10[0].Lib[0].SubListb[0].Lii3[0].CheckBox04[0]",
          "description": "This case is exempt from judicial arbitration under rule 3.811 of the California Rules of Court or from civil action  mediation under Code of Civil Procedure section 1775 et seq. ",
          "type": "Button"
        },
        {
          "name": "CM-110[0].Page2[0].List10[0].Lib[0].SubListb[0].Lii3[0].FillText18[0]",
          "description": "specify exemption",
          "type": "Text"
        },
        {
          "name": "CM-110[0].Page3[0].List10[0].Lic[0].Table1[0].Row1[0].sub1[0].limitedch[0]",
          "description": "check here if The party or parties completing this form are willing to participate in the following ADR processes: Mediation",
          "type": "Button"
        },
        {
          "name": "CM-110[0].Page3[0].List10[0].Lic[0].Table1[0].Row1[0].sub2[0].partystatement10[0]",
          "description": "Mediation session not yet scheduled",
          "type": "Button"
        },
        {
          "name": "CM-110[0].Page3[0].List10[0].Lic[0].Table1[0].Row1[0].sub2[0].partystatement2[0]",
          "description": "Mediation session scheduled for",
          "type": "Button"
        },
        {
          "name": "CM-110[0].Page3[0].List10[0].Lic[0].Table1[0].Row1[0].sub2[0].DateField2[0]",
          "description": "date",
          "type": "Text"
        },
        {
          "name": "CM-110[0].Page3[0].List10[0].Lic[0].Table1[0].Row1[0].sub2[0].partystatement3[0]",
          "description": "Agreed to complete mediation by",
          "type": "Button"
        },
        {
          "name": "CM-110[0].Page3[0].List10[0].Lic[0].Table1[0].Row1[0].sub2[0].DateField3[0]",
          "description": "date",
          "type": "Text"
        },
        {
          "name": "CM-110[0].Page3[0].List10[0].Lic[0].Table1[0].Row1[0].sub2[0].partystatement4[0]",
          "description": "Mediation completed on",
          "type": "Button"
        },
        {
          "name": "CM-110[0].Page3[0].List10[0].Lic[0].Table1[0].Row1[0].sub2[0].DateField4[0]",
          "description": "date",
          "type": "Text"
        },
        {
          "name": "CM-110[0].Page3[0].List10[0].Lic[0].Table1[0].Row2[0].sub3[0].limitedch1[0]",
          "description": "check here if The party or parties completing this form are willing to participate in the following ADR processes: Settlement conference",
          "type": "Button"
        },
        {
          "name": "CM-110[0].Page3[0].List10[0].Lic[0].Table1[0].Row2[0].sub4[0].partystatement5[0]",
          "description": "Settlement conference not yet scheduled",
          "type": "Button"
        },
        {
          "name": "CM-110[0].Page3[0].List10[0].Lic[0].Table1[0].Row2[0].sub4[0].partystatement6[0]",
          "description": "Settlement conference scheduled for",
          "type": "Button"
        },
        {
          "name": "CM-110[0].Page3[0].List10[0].Lic[0].Table1[0].Row2[0].sub4[0].DateField5[0]",
          "description": "date",
          "type": "Text"
        },
        {
          "name": "CM-110[0].Page3[0].List10[0].Lic[0].Table1[0].Row2[0].sub4[0].partystatement7[0]",
          "description": "Agreed to complete settlement conference by",
          "type": "Button"
        },
        {
          "name": "CM-110[0].Page3[0].List10[0].Lic[0].Table1[0].Row2[0].sub4[0].DateField6[0]",
          "description": "date",
          "type": "Text"
        },
        {
          "name": "CM-110[0].Page3[0].List10[0].Lic[0].Table1[0].Row2[0].sub4[0].partystatement8[0]",
          "description": "Settlement conference completed on",
          "type": "Button"
        },
        {
          "name": "CM-110[0].Page3[0].List10[0].Lic[0].Table1[0].Row2[0].sub4[0].DateField7[0]",
          "description": "date",
          "type": "Text"
        },
        {
          "name": "CM-110[0].Page3[0].List10[0].Lic[0].Table1[0].Row3[0].sub5[0].limitedch2[0]",
          "description": "check here if The party or parties completing this form are willing to participate in the following ADR processes: Neutral evaluation",
          "type": "Button"
        },
        {
          "name": "CM-110[0].Page3[0].List10[0].Lic[0].Table1[0].Row3[0].sub6[0].partystatement9[0]",
          "description": "Neutral evaluation not yet scheduled",
          "type": "Button"
        },
        {
          "name": "CM-110[0].Page3[0].List10[0].Lic[0].Table1[0].Row3[0].sub6[0].partystatement10[0]",
          "description": "Neutral evaluation scheduled for",
          "type": "Button"
        },
        {
          "name": "CM-110[0].Page3[0].List10[0].Lic[0].Table1[0].Row3[0].sub6[0].DateField8[0]",
          "description": "date",
          "type": "Text"
        },
        {
          "name": "CM-110[0].Page3[0].List10[0].Lic[0].Table1[0].Row3[0].sub6[0].partystatement11[0]",
          "description": "Agreed to complete neutral evaluation by",
          "type": "Button"
        },
        {
          "name": "CM-110[0].Page3[0].List10[0].Lic[0].Table1[0].Row3[0].sub6[0].DateField9[0]",
          "description": "date",
          "type": "Text"
        },
        {
          "name": "CM-110[0].Page3[0].List10[0].Lic[0].Table1[0].Row3[0].sub6[0].partystatement12[0]",
          "description": "Neutral evaluation completed on",
          "type": "Button"
        },
        {
          "name": "CM-110[0].Page3[0].List10[0].Lic[0].Table1[0].Row3[0].sub6[0].DateField10[0]",
          "description": "date",
          "type": "Text"
        },
        {
          "name": "CM-110[0].Page3[0].List10[0].Lic[0].Table1[0].Row4[0].sub7[0].limitedch3[0]",
          "description": "check here if The party or parties completing this form are willing to participate in the following ADR processes: Non binding judicial arbitration",
          "type": "Button"
        },
        {
          "name": "CM-110[0].Page3[0].List10[0].Lic[0].Table1[0].Row4[0].sub8[0].partystatement13[0]",
          "description": "Judicial arbitration not yet scheduled",
          "type": "Button"
        },
        {
          "name": "CM-110[0].Page3[0].List10[0].Lic[0].Table1[0].Row4[0].sub8[0].partystatement14[0]",
          "description": "Judicial arbitration scheduled for",
          "type": "Button"
        },
        {
          "name": "CM-110[0].Page3[0].List10[0].Lic[0].Table1[0].Row4[0].sub8[0].DateField11[0]",
          "description": "date",
          "type": "Text"
        },
        {
          "name": "CM-110[0].Page3[0].List10[0].Lic[0].Table1[0].Row4[0].sub8[0].partystatement15[0]",
          "description": "Agreed to complete judicial arbitration by",
          "type": "Button"
        },
        {
          "name": "CM-110[0].Page3[0].List10[0].Lic[0].Table1[0].Row4[0].sub8[0].DateField12[0]",
          "description": "date",
          "type": "Text"
        },
        {
          "name": "CM-110[0].Page3[0].List10[0].Lic[0].Table1[0].Row4[0].sub8[0].partystatement16[0]",
          "description": "Judicial arbitration completed on",
          "type": "Button"
        },
        {
          "name": "CM-110[0].Page3[0].List10[0].Lic[0].Table1[0].Row4[0].sub8[0].DateField13[0]",
          "description": "date",
          "type": "Text"
        },
        {
          "name": "CM-110[0].Page3[0].List10[0].Lic[0].Table1[0].Row5[0].sub9[0].limitedch4[0]",
          "description": "check here if The party or parties completing this form are willing to participate in the following ADR processes: Binding private arbitration",
          "type": "Button"
        },
        {
          "name": "CM-110[0].Page3[0].List10[0].Lic[0].Table1[0].Row5[0].sub10[0].partystatement17[0]",
          "description": "Private arbitration not yet scheduled",
          "type": "Button"
        },
        {
          "name": "CM-110[0].Page3[0].List10[0].Lic[0].Table1[0].Row5[0].sub10[0].partystatement18[0]",
          "description": "Private arbitration scheduled for",
          "type": "Button"
        },
        {
          "name": "CM-110[0].Page3[0].List10[0].Lic[0].Table1[0].Row5[0].sub10[0].DateField14[0]",
          "description": "date",
          "type": "Text"
        },
        {
          "name": "CM-110[0].Page3[0].List10[0].Lic[0].Table1[0].Row5[0].sub10[0].partystatement19[0]",
          "description": "Agreed to complete private arbitration by",
          "type": "Button"
        },
        {
          "name": "CM-110[0].Page3[0].List10[0].Lic[0].Table1[0].Row5[0].sub10[0].DateField15[0]",
          "description": "date",
          "type": "Text"
        },
        {
          "name": "CM-110[0].Page3[0].List10[0].Lic[0].Table1[0].Row5[0].sub10[0].partystatement20[0]",
          "description": "Private arbitration completed on",
          "type": "Button"
        },
        {
          "name": "CM-110[0].Page3[0].List10[0].Lic[0].Table1[0].Row5[0].sub10[0].DateField16[0]",
          "description": "date",
          "type": "Text"
        },
        {
          "name": "CM-110[0].Page3[0].List10[0].Lic[0].Table1[0].Row6[0].sub11[0].limitedch5[0]",
          "description": "check here if the party or parties completing this form are willing to participate in the following ADR processes: Other",
          "type": "Button"
        },
        {
          "name": "CM-110[0].Page3[0].List10[0].Lic[0].Table1[0].Row6[0].sub12[0].partystatement21[0]",
          "description": "ADR session not yet scheduled",
          "type": "Button"
        },
        {
          "name": "CM-110[0].Page3[0].List10[0].Lic[0].Table1[0].Row6[0].sub12[0].partystatement22[0]",
          "description": "ADR session scheduled for",
          "type": "Button"
        },
        {
          "name": "CM-110[0].Page3[0].List10[0].Lic[0].Table1[0].Row6[0].sub12[0].DateField17[0]",
          "description": "date",
          "type": "Text"
        },
        {
          "name": "CM-110[0].Page3[0].List10[0].Lic[0].Table1[0].Row6[0].sub12[0].partystatement23[0]",
          "description": "Agreed to complete ADR session by",
          "type": "Button"
        },
        {
          "name": "CM-110[0].Page3[0].List10[0].Lic[0].Table1[0].Row6[0].sub12[0].DateField18[0]",
          "description": "date",
          "type": "Text"
        },
        {
          "name": "CM-110[0].Page3[0].List10[0].Lic[0].Table1[0].Row6[0].sub12[0].partystatement19[0]",
          "description": "ADR completed on",
          "type": "Button"
        },
        {
          "name": "CM-110[0].Page3[0].List10[0].Lic[0].Table1[0].Row6[0].sub12[0].DateField19[0]",
          "description": "date",
          "type": "Text"
        },
        {
          "name": "CM-110[0].Page4[0].List11[0].Lia[0].Ch31[0]",
          "description": "Insurance carrier, if any, for party filing this statement",
          "type": "Button"
        },
        {
          "name": "CM-110[0].Page4[0].List11[0].Lia[0].Name1[0]",
          "description": "name",
          "type": "Text"
        },
        {
          "name": "CM-110[0].Page4[0].List11[0].Lib[0].Yes10[0]",
          "description": "yes",
          "type": "Button"
        },
        {
          "name": "CM-110[0].Page4[0].List11[0].Lib[0].Yes10[1]",
          "description": "No",
          "type": "Button"
        },
        {
          "name": "CM-110[0].Page4[0].List11[0].Lic[0].Ch32[0]",
          "description": "Coverage issues will significantly affect resolution of this case",
          "type": "Button"
        },
        {
          "name": "CM-110[0].Page4[0].List11[0].Lic[0].Field1[0]",
          "description": "Explain",
          "type": "Text"
        },
        {
          "name": "CM-110[0].Page4[0].List12[0].item12[0].counsel15[0]",
          "description": "Bankruptcy",
          "type": "Button"
        },
        {
          "name": "CM-110[0].Page4[0].List12[0].item12[0].counsel15[1]",
          "description": "Other",
          "type": "Button"
        },
        {
          "name": "CM-110[0].Page4[0].List12[0].item12[0].specify12[0]",
          "description": "Specify",
          "type": "Text"
        },
        {
          "name": "CM-110[0].Page4[0].List12[0].item12[0].Status[0]",
          "description": "Status",
          "type": "Text"
        },
        {
          "name": "CM-110[0].Page4[0].List13[0].Lia[0].Ch35[0]",
          "description": "There are companion, underlying, or related cases.",
          "type": "Button"
        },
        {
          "name": "CM-110[0].Page4[0].List13[0].Lia[0].SubLista[0].Lii1[0].Field2[0]",
          "description": "Name of case:",
          "type": "Text"
        },
        {
          "name": "CM-110[0].Page4[0].List13[0].Lia[0].SubLista[0].Lii2[0].Field3[0]",
          "description": "Name of court:",
          "type": "Text"
        },
        {
          "name": "CM-110[0].Page4[0].List13[0].Lia[0].SubLista[0].Lii3[0].Field4[0]",
          "description": "Case number:",
          "type": "Text"
        },
        {
          "name": "CM-110[0].Page4[0].List13[0].Lia[0].SubLista[0].Lii4[0].Field5[0]",
          "description": "Status:",
          "type": "Text"
        },
        {
          "name": "CM-110[0].Page4[0].List13[0].Lia[0].limitedatt11[0]",
          "description": "Additional cases are described in Attachment 13a.",
          "type": "Button"
        },
        {
          "name": "CM-110[0].Page4[0].List13[0].Lib[0].Field6[0]",
          "description": "will be filed by (name party)",
          "type": "Text"
        },
        {
          "name": "CM-110[0].Page4[0].List13[0].Lib[0].RB2Choices12[0]",
          "description": "A motion to",
          "type": "Button"
        },
        {
          "name": "CM-110[0].Page4[0].List13[0].Lib[0].RB2Choices13[0]",
          "description": "consolidate",
          "type": "Button"
        },
        {
          "name": "CM-110[0].Page4[0].List13[0].Lib[0].RB2Choices13[1]",
          "description": "coordinate",
          "type": "Button"
        },
        {
          "name": "CM-110[0].Page4[0].List14[0].item14[0].Ch37[0]",
          "description": "The party or parties intend to file a motion for an order bifurcating, severing, or coordinating the following issues or causes of action",
          "type": "Button"
        },
        {
          "name": "CM-110[0].Page4[0].List14[0].item14[0].Field7[0]",
          "description": "specify moving party, type of motion, and reasons",
          "type": "Text"
        },
        {
          "name": "CM-110[0].Page4[0].List15[0].item15[0].Ch39[0]",
          "description": "The party or parties expect to file the following motions before trial",
          "type": "Button"
        },
        {
          "name": "CM-110[0].Page4[0].List15[0].item15[0].Field16[0]",
          "description": "Specify moving party, type of motion and issues",
          "type": "Text"
        },
        {
          "name": "CM-110[0].Page4[0].List16[0].Lia[0].disco[0]",
          "description": "The party or parties have completed all discovery.",
          "type": "Button"
        },
        {
          "name": "CM-110[0].Page4[0].List16[0].Lib[0].disco1[0]",
          "description": "The following discovery will be completed by the date specified (describe all anticipated discovery):",
          "type": "Button"
        },
        {
          "name": "CM-110[0].Page4[0].List16[0].Lib[0].Table[0].AdmProceedingTitle_ft1[0]",
          "description": "Enter Party field 1",
          "type": "Text"
        },
        {
          "name": "CM-110[0].Page4[0].List16[0].Lib[0].Table[0].AdmProceedingTitle_ft2[0]",
          "description": "Enter Description field 1",
          "type": "Text"
        },
        {
          "name": "CM-110[0].Page4[0].List16[0].Lib[0].Table[0].AdmProceedingDate_ft3[0]",
          "description": "Enter Date field 1",
          "type": "Text"
        },
        {
          "name": "CM-110[0].Page4[0].List16[0].Lib[0].Table[0].AdmProceedingTitle_ft4[0]",
          "description": "Enter Party field 2",
          "type": "Text"
        },
        {
          "name": "CM-110[0].Page4[0].List16[0].Lib[0].Table[0].AdmProceedingTitle_ft5[0]",
          "description": "Enter Description field 2",
          "type": "Text"
        },
        {
          "name": "CM-110[0].Page4[0].List16[0].Lib[0].Table[0].AdmProceedingDate_ft6[0]",
          "description": "Enter Date field 2",
          "type": "Text"
        },
        {
          "name": "CM-110[0].Page4[0].List16[0].Lib[0].Table[0].AdmProceedingTitle_ft7[0]",
          "description": "Enter Party field 3",
          "type": "Text"
        },
        {
          "name": "CM-110[0].Page4[0].List16[0].Lib[0].Table[0].AdmProceedingTitle_ft8[0]",
          "description": "Enter Description field 3",
          "type": "Text"
        },
        {
          "name": "CM-110[0].Page4[0].List16[0].Lib[0].Table[0].AdmProceedingDate_ft9[0]",
          "description": "Enter Date field 3",
          "type": "Text"
        },
        {
          "name": "CM-110[0].Page4[0].List16[0].Lib[0].Table[0].AdmProceedingTitle_ft10[0]",
          "description": "Enter Party field 4",
          "type": "Text"
        },
        {
          "name": "CM-110[0].Page4[0].List16[0].Lib[0].Table[0].AdmProceedingTitle_ft11[0]",
          "description": "Enter Description field 4",
          "type": "Text"
        },
        {
          "name": "CM-110[0].Page4[0].List16[0].Lib[0].Table[0].AdmProceedingDate_ft12[0]",
          "description": "Enter Date field 4",
          "type": "Text"
        },
        {
          "name": "CM-110[0].Page4[0].List16[0].Lib[0].Table[0].AdmProceedingTitle_ft13[0]",
          "description": "Enter Party field 5",
          "type": "Text"
        },
        {
          "name": "CM-110[0].Page4[0].List16[0].Lib[0].Table[0].AdmProceedingTitle_ft[0]",
          "description": "Enter Description field 5",
          "type": "Text"
        },
        {
          "name": "CM-110[0].Page4[0].List16[0].Lib[0].Table[0].AdmProceedingDate_ft[0]",
          "description": "Enter Date field 5",
          "type": "Text"
        },
        {
          "name": "CM-110[0].Page4[0].List16[0].Lic[0].Ch40[0]",
          "description": "The following discovery issues, including issues regarding the discovery of electronically stored information, are anticipated",
          "type": "Button"
        },
        {
          "name": "CM-110[0].Page4[0].List16[0].Lic[0].Field21[0]",
          "description": "specify",
          "type": "Text"
        },
        {
          "name": "CM-110[0].#pageSet[0].MPLast[0].FooterButtons[0].Print[0]",
          "description": "Print this form",
          "type": "Button"
        },
        {
          "name": "CM-110[0].#pageSet[0].MPLast[0].FooterButtons[0].Save[0]",
          "description": "Save this form",
          "type": "Button"
        },
        {
          "name": "CM-110[0].#pageSet[0].MPLast[0].FooterButtons[0].Reset[0]",
          "description": "Clear this form",
          "type": "Button"
        },
        {
          "name": "CM-110[0].#pageSet[0].MPLast[0].FooterButtons[0].Warning[0]",
          "description": "For your protection and privacy, please press the Clear This Form button after you have printed the form.",
          "type": "Button"
        },
        {
          "name": "CM-110[0].Page5[0].List17[0].Lia[0].estimation2[0]",
          "description": "This is a limited civil case (i.e., the amount demanded is $35,000 or less) and the economic litigation procedures in Code\rof Civil Procedure sections 90-98 will apply to this case.",
          "type": "Button"
        },
        {
          "name": "CM-110[0].Page5[0].List17[0].Lib[0].estimation2[0]",
          "description": "This is a limited civil case and a motion to withdraw the case from the economic litigation procedures or for additional\rdiscovery will be filed",
          "type": "Button"
        },
        {
          "name": "CM-110[0].Page5[0].List17[0].Lib[0].Field26[0]",
          "description": "if checked, explain specifically why economic litigation procedures relating to discovery or trial should not apply to this case",
          "type": "Text"
        },
        {
          "name": "CM-110[0].Page5[0].List18[0].item18[0].Ch42[0]",
          "description": "The party or parties request that the following additional matters be considered or determined at the case management\rconference",
          "type": "Button"
        },
        {
          "name": "CM-110[0].Page5[0].List18[0].item18[0].Field42[0]",
          "description": "specify",
          "type": "Text"
        },
        {
          "name": "CM-110[0].Page5[0].List19[0].Lia[0].estimation3[0]",
          "description": "The party or parties have met and conferred with all parties on all subjects required by rule 3.724 of the California Rules\rof Court",
          "type": "Button"
        },
        {
          "name": "CM-110[0].Page5[0].List19[0].Lia[0].Field43[0]",
          "description": "if not, explain",
          "type": "Text"
        },
        {
          "name": "CM-110[0].Page5[0].List19[0].Lib[0].estimation3[0]",
          "description": "After meeting and conferring as required by rule 3.724 of the California Rules of Court, the parties agree on the following",
          "type": "Button"
        },
        {
          "name": "CM-110[0].Page5[0].List19[0].Lib[0].FillText44[0]",
          "description": "spcify",
          "type": "Text"
        },
        {
          "name": "CM-110[0].Page5[0].List20[0].NumberOfPages[0].Numbers[0]",
          "description": "Total number of pages attached (if any):",
          "type": "Text"
        },
        {
          "name": "CM-110[0].Page5[0].Sign[0].SigDate1[0]",
          "description": "Date",
          "type": "Text"
        },
        {
          "name": "CM-110[0].Page5[0].Sign[0].SigName1[0]",
          "description": "Type or print name",
          "type": "Text"
        },
        {
          "name": "CM-110[0].Page5[0].Sign[0].SigName2[0]",
          "description": "Type or print name",
          "type": "Text"
        },
        {
          "name": "CM-110[0].Page5[0].Sign[0].addsign24[0]",
          "description": "Additional signatures are attached.",
          "type": "Button"
        }
      ]
    }
  ],
  "allFields": [
    {
      "FieldType": "Text",
      "FieldName": "CM-110[0].Page1[0].P1Caption[0].captionSub[0].CaseNumber[0].caseNumber[0]",
      "FieldNameAlt": "Case number",
      "FieldFlags": "8388608",
      "FieldValue": "",
      "FieldJustification": "Left"
    },
    {
      "FieldType": "Text",
      "FieldName": "CM-110[0].Page1[0].P1Caption[0].AttyPartyInfo[0].AttyBarNo[0]",
      "FieldNameAlt": "State Bar number",
      "FieldFlags": "8388608",
      "FieldValue": "",
      "FieldJustification": "Left"
    },
    {
      "FieldType": "Text",
      "FieldName": "CM-110[0].Page1[0].P1Caption[0].AttyPartyInfo[0].Name[0]",
      "FieldNameAlt": "Name",
      "FieldFlags": "8388608",
      "FieldValue": "",
      "FieldJustification": "Left"
    },
    {
      "FieldType": "Text",
      "FieldName": "CM-110[0].Page1[0].P1Caption[0].AttyPartyInfo[0].AttyFirm[0]",
      "FieldNameAlt": "FIrm name",
      "FieldFlags": "8388608",
      "FieldValue": "",
      "FieldJustification": "Left"
    },
    {
      "FieldType": "Text",
      "FieldName": "CM-110[0].Page1[0].P1Caption[0].AttyPartyInfo[0].Street[0]",
      "FieldNameAlt": "Street address",
      "FieldFlags": "8388608",
      "FieldValue": "",
      "FieldJustification": "Left"
    },
    {
      "FieldType": "Text",
      "FieldName": "CM-110[0].Page1[0].P1Caption[0].AttyPartyInfo[0].City[0]",
      "FieldNameAlt": "City",
      "FieldFlags": "8388608",
      "FieldValue": "",
      "FieldJustification": "Left"
    },
    {
      "FieldType": "Text",
      "FieldName": "CM-110[0].Page1[0].P1Caption[0].AttyPartyInfo[0].State[0]",
      "FieldNameAlt": "State",
      "FieldFlags": "0",
      "FieldValue": "",
      "FieldJustification": "Left"
    },
    {
      "FieldType": "Text",
      "FieldName": "CM-110[0].Page1[0].P1Caption[0].AttyPartyInfo[0].Zip[0]",
      "FieldNameAlt": "Zip code",
      "FieldFlags": "8388608",
      "FieldValue": "",
      "FieldJustification": "Left"
    },
    {
      "FieldType": "Text",
      "FieldName": "CM-110[0].Page1[0].P1Caption[0].AttyPartyInfo[0].Phone[0]",
      "FieldNameAlt": "Telephone number:",
      "FieldFlags": "8388608",
      "FieldValue": "",
      "FieldJustification": "Left"
    },
    {
      "FieldType": "Text",
      "FieldName": "CM-110[0].Page1[0].P1Caption[0].AttyPartyInfo[0].Fax[0]",
      "FieldNameAlt": "Fax number:",
      "FieldFlags": "8388608",
      "FieldValue": "",
      "FieldJustification": "Left"
    },
    {
      "FieldType": "Text",
      "FieldName": "CM-110[0].Page1[0].P1Caption[0].AttyPartyInfo[0].Email[0]",
      "FieldNameAlt": "Email address",
      "FieldFlags": "8388608",
      "FieldValue": "",
      "FieldJustification": "Left"
    },
    {
      "FieldType": "Text",
      "FieldName": "CM-110[0].Page1[0].P1Caption[0].AttyPartyInfo[0].AttyFor[0]",
      "FieldNameAlt": "Attorney for (name)",
      "FieldFlags": "8388608",
      "FieldValue": "",
      "FieldJustification": "Left"
    },
    {
      "FieldType": "Text",
      "FieldName": "CM-110[0].Page1[0].P1Caption[0].CourtInfo[0].CrtCounty[0]",
      "FieldNameAlt": "Superior Court of California, County of",
      "FieldFlags": "8388608",
      "FieldValue": "",
      "FieldJustification": "Left"
    },
    {
      "FieldType": "Text",
      "FieldName": "CM-110[0].Page1[0].P1Caption[0].CourtInfo[0].CrtStreet[0]",
      "FieldNameAlt": "Street address",
      "FieldFlags": "8388608",
      "FieldValue": "",
      "FieldJustification": "Left"
    },
    {
      "FieldType": "Text",
      "FieldName": "CM-110[0].Page1[0].P1Caption[0].CourtInfo[0].CrtMailingAdd[0]",
      "FieldNameAlt": "Mailing address",
      "FieldFlags": "8388608",
      "FieldValue": "",
      "FieldJustification": "Left"
    },
    {
      "FieldType": "Text",
      "FieldName": "CM-110[0].Page1[0].P1Caption[0].CourtInfo[0].CrtCityZip[0]",
      "FieldNameAlt": "City and zip code",
      "FieldFlags": "8388608",
      "FieldValue": "",
      "FieldJustification": "Left"
    },
    {
      "FieldType": "Text",
      "FieldName": "CM-110[0].Page1[0].P1Caption[0].CourtInfo[0].CrtBranch[0]",
      "FieldNameAlt": "Branch name",
      "FieldFlags": "8388608",
      "FieldValue": "",
      "FieldJustification": "Left"
    },
    {
      "FieldType": "Text",
      "FieldName": "CM-110[0].Page1[0].P1Caption[0].TitlePartyName[0].Party1[0]",
      "FieldNameAlt": "PLAINTIFF or PETITIONER:",
      "FieldFlags": "8388608",
      "FieldValue": "",
      "FieldJustification": "Left"
    },
    {
      "FieldType": "Text",
      "FieldName": "CM-110[0].Page1[0].P1Caption[0].TitlePartyName[0].Party2[0]",
      "FieldNameAlt": "DEFENDANT or RESPONDENT:",
      "FieldFlags": "8388608",
      "FieldValue": "",
      "FieldJustification": "Left"
    },
    {
      "FieldType": "Button",
      "FieldName": "CM-110[0].Page1[0].P1Caption[0].FormTitle[0].limit12[0]",
      "FieldNameAlt": "UNLIMITED CASE (Amount demanded exceeds 35,000 dollar)",
      "FieldFlags": "0",
      "FieldValue": "",
      "FieldJustification": "Left"
    },
    {
      "FieldType": "Button",
      "FieldName": "CM-110[0].Page1[0].P1Caption[0].FormTitle[0].limit12[1]",
      "FieldNameAlt": "LIMITED CASE (Amount demanded is 35,000 dollar or less)",
      "FieldFlags": "0",
      "FieldValue": "",
      "FieldJustification": "Left"
    },
    {
      "FieldType": "Text",
      "FieldName": "CM-110[0].Page1[0].Note[0].Date1[0]",
      "FieldNameAlt": "Date",
      "FieldFlags": "8388608",
      "FieldValue": "",
      "FieldJustification": "Left"
    },
    {
      "FieldType": "Text",
      "FieldName": "CM-110[0].Page1[0].Note[0].Time1[0]",
      "FieldNameAlt": "Time",
      "FieldFlags": "8388608",
      "FieldValue": "",
      "FieldJustification": "Left"
    },
    {
      "FieldType": "Text",
      "FieldName": "CM-110[0].Page1[0].Note[0].Dept1[0]",
      "FieldNameAlt": "Department",
      "FieldFlags": "8388608",
      "FieldValue": "",
      "FieldJustification": "Left"
    },
    {
      "FieldType": "Text",
      "FieldName": "CM-110[0].Page1[0].Note[0].Div1[0]",
      "FieldNameAlt": "Division",
      "FieldFlags": "8388608",
      "FieldValue": "",
      "FieldJustification": "Left"
    },
    {
      "FieldType": "Text",
      "FieldName": "CM-110[0].Page1[0].Note[0].Rm1[0]",
      "FieldNameAlt": "Room",
      "FieldFlags": "8388608",
      "FieldValue": "",
      "FieldJustification": "Left"
    },
    {
      "FieldType": "Text",
      "FieldName": "CM-110[0].Page1[0].Note[0].FillText1[0]",
      "FieldNameAlt": "Address of court (if different from the address above):",
      "FieldFlags": "8388608",
      "FieldValue": "",
      "FieldJustification": "Left"
    },
    {
      "FieldType": "Button",
      "FieldName": "CM-110[0].Page1[0].Note[0].Ch1[0]",
      "FieldNameAlt": "Notice of Intent to Appear by Telephone,",
      "FieldFlags": "0",
      "FieldValue": "",
      "FieldJustification": "Left"
    },
    {
      "FieldType": "Text",
      "FieldName": "CM-110[0].Page1[0].Note[0].TextField1[0]",
      "FieldNameAlt": "by (name):",
      "FieldFlags": "8388608",
      "FieldValue": "",
      "FieldJustification": "Left"
    },
    {
      "FieldType": "Button",
      "FieldName": "CM-110[0].Page1[0].List1[0].Lia[0].partystatement1[0]",
      "FieldNameAlt": "This statement is submitted by party",
      "FieldFlags": "0",
      "FieldValue": "",
      "FieldJustification": "Left"
    },
    {
      "FieldType": "Text",
      "FieldName": "CM-110[0].Page1[0].List1[0].Lia[0].TextField2[0]",
      "FieldNameAlt": "name",
      "FieldFlags": "8388608",
      "FieldValue": "",
      "FieldJustification": "Left"
    },
    {
      "FieldType": "Button",
      "FieldName": "CM-110[0].Page1[0].List1[0].Lib[0].partystatement1[0]",
      "FieldNameAlt": "This statement is submitted jointly by parties",
      "FieldFlags": "0",
      "FieldValue": "",
      "FieldJustification": "Left"
    },
    {
      "FieldType": "Text",
      "FieldName": "CM-110[0].Page1[0].List1[0].Lib[0].TextField3[0]",
      "FieldNameAlt": "names",
      "FieldFlags": "8388608",
      "FieldValue": "",
      "FieldJustification": "Left"
    },
    {
      "FieldType": "Text",
      "FieldName": "CM-110[0].Page1[0].List2[0].Lia[0].Date3[0]",
      "FieldNameAlt": "The complaint was filed on date",
      "FieldFlags": "8388608",
      "FieldValue": "",
      "FieldJustification": "Left"
    },
    {
      "FieldType": "Button",
      "FieldName": "CM-110[0].Page1[0].List2[0].Lib[0].Ch3[0]",
      "FieldNameAlt": "The cross-complaint, if any, was filed on",
      "FieldFlags": "0",
      "FieldValue": "",
      "FieldJustification": "Left"
    },
    {
      "FieldType": "Text",
      "FieldName": "CM-110[0].Page1[0].List2[0].Lib[0].Date4[0]",
      "FieldNameAlt": "date",
      "FieldFlags": "8388608",
      "FieldValue": "",
      "FieldJustification": "Left"
    },
    {
      "FieldType": "Button",
      "FieldName": "CM-110[0].Page1[0].List3[0].Lia[0].limitedee[0]",
      "FieldNameAlt": "All parties named in the complaint and cross-complaint have been served, have appeared, or have been dismissed.",
      "FieldFlags": "0",
      "FieldValue": "",
      "FieldJustification": "Left"
    },
    {
      "FieldType": "Button",
      "FieldName": "CM-110[0].Page1[0].List3[0].lib[0].Ch5[0]",
      "FieldNameAlt": "The following parties named in the complaint or cross-complaint",
      "FieldFlags": "0",
      "FieldValue": "",
      "FieldJustification": "Left"
    },
    {
      "FieldType": "Button",
      "FieldName": "CM-110[0].Page1[0].List3[0].lib[0].sublist[0].Lii1[0].Ch6[0]",
      "FieldNameAlt": "have not been served",
      "FieldFlags": "0",
      "FieldValue": "",
      "FieldJustification": "Left"
    },
    {
      "FieldType": "Text",
      "FieldName": "CM-110[0].Page1[0].List3[0].lib[0].sublist[0].Lii1[0].TextField4[0]",
      "FieldNameAlt": "(specify names and explain why not):",
      "FieldFlags": "8388608",
      "FieldValue": "",
      "FieldJustification": "Left"
    },
    {
      "FieldType": "Button",
      "FieldName": "CM-110[0].Page1[0].List3[0].lib[0].sublist[0].Lii2[0].Ch7[0]",
      "FieldNameAlt": "have been served but have not appeared and have not been dismissed",
      "FieldFlags": "0",
      "FieldValue": "",
      "FieldJustification": "Left"
    },
    {
      "FieldType": "Text",
      "FieldName": "CM-110[0].Page1[0].List3[0].lib[0].sublist[0].Lii2[0].TextField5[0]",
      "FieldNameAlt": "(specify names):",
      "FieldFlags": "8388608",
      "FieldValue": "",
      "FieldJustification": "Left"
    },
    {
      "FieldType": "Button",
      "FieldName": "CM-110[0].Page1[0].List3[0].lib[0].sublist[0].li3[0].Ch8[0]",
      "FieldNameAlt": "Have had a default entered against them",
      "FieldFlags": "0",
      "FieldValue": "",
      "FieldJustification": "Left"
    },
    {
      "FieldType": "Text",
      "FieldName": "CM-110[0].Page1[0].List3[0].lib[0].sublist[0].li3[0].TextField7[0]",
      "FieldNameAlt": "specify names:",
      "FieldFlags": "8388608",
      "FieldValue": "",
      "FieldJustification": "Left"
    },
    {
      "FieldType": "Button",
      "FieldName": "CM-110[0].Page1[0].List3[0].Lic[0].Ch9[0]",
      "FieldNameAlt": "The following additional parties may be added ",
      "FieldFlags": "0",
      "FieldValue": "",
      "FieldJustification": "Left"
    },
    {
      "FieldType": "Text",
      "FieldName": "CM-110[0].Page1[0].List3[0].Lic[0].TextField9[0]",
      "FieldNameAlt": "specify names, nature of involvement in case, and date by which they may be served:",
      "FieldFlags": "8392704",
      "FieldValue": "",
      "FieldJustification": "Left"
    },
    {
      "FieldType": "Text",
      "FieldName": "CM-110[0].Page1[0].List4[0].Lia[0].FillText11[0]",
      "FieldNameAlt": "Describe, including causes of action",
      "FieldFlags": "8392704",
      "FieldValue": "",
      "FieldJustification": "Left"
    },
    {
      "FieldType": "Button",
      "FieldName": "CM-110[0].Page1[0].List4[0].Lia[0].Ch10[0]",
      "FieldNameAlt": "complaint",
      "FieldFlags": "0",
      "FieldValue": "",
      "FieldJustification": "Left"
    },
    {
      "FieldType": "Button",
      "FieldName": "CM-110[0].Page1[0].List4[0].Lia[0].Ch10[1]",
      "FieldNameAlt": "cross-complaint",
      "FieldFlags": "0",
      "FieldValue": "",
      "FieldJustification": "Left"
    },
    {
      "FieldType": "Text",
      "FieldName": "CM-110[0].Page2[0].PxCaption[0].TitlePartyName[0].Party1[0]",
      "FieldNameAlt": "PLAINTIFF or PETITIONER:",
      "FieldFlags": "8388609",
      "FieldValue": "",
      "FieldJustification": "Left"
    },
    {
      "FieldType": "Text",
      "FieldName": "CM-110[0].Page2[0].PxCaption[0].TitlePartyName[0].Party2[0]",
      "FieldNameAlt": "DEFENDANT or RESPONDENT:",
      "FieldFlags": "8388609",
      "FieldValue": "",
      "FieldJustification": "Left"
    },
    {
      "FieldType": "Text",
      "FieldName": "CM-110[0].Page2[0].PxCaption[0].CaseNumber[0].caseNumber[0]",
      "FieldNameAlt": "Case number",
      "FieldFlags": "8388609",
      "FieldValue": "",
      "FieldJustification": "Left"
    },
    {
      "FieldType": "Text",
      "FieldName": "CM-110[0].Page2[0].List4[0].Lib[0].FillText13[0]",
      "FieldNameAlt": "Provide a brief statement of the case, including any damages (if personal injury damages are sought, specify the injury and\rdamages claimed, including medical expenses to date [indicate source and amount], estimated future medical expenses, lost\rearnings to date, and estimated future lost earnings; if equitable relief is sought, describe the nature of the relief):",
      "FieldFlags": "8392704",
      "FieldValue": "",
      "FieldJustification": "Left"
    },
    {
      "FieldType": "Button",
      "FieldName": "CM-110[0].Page2[0].List4[0].Ch15[0]",
      "FieldNameAlt": "(If more space is needed, check this box and attach a page designated as Attachment 4b.)",
      "FieldFlags": "0",
      "FieldValue": "",
      "FieldJustification": "Left"
    },
    {
      "FieldType": "Text",
      "FieldName": "CM-110[0].Page2[0].List5[0].item5[0].FillText16[0]",
      "FieldNameAlt": "If more than one party, provide the name of each party requesting a jury trial",
      "FieldFlags": "8388608",
      "FieldValue": "",
      "FieldJustification": "Left"
    },
    {
      "FieldType": "Button",
      "FieldName": "CM-110[0].Page2[0].List5[0].item5[0].jurytrial1[0]",
      "FieldNameAlt": "a jury triaI",
      "FieldFlags": "0",
      "FieldValue": "",
      "FieldJustification": "Left"
    },
    {
      "FieldType": "Button",
      "FieldName": "CM-110[0].Page2[0].List5[0].item5[0].jurytrial1[1]",
      "FieldNameAlt": "a nonjury trial.",
      "FieldFlags": "0",
      "FieldValue": "",
      "FieldJustification": "Left"
    },
    {
      "FieldType": "Button",
      "FieldName": "CM-110[0].Page2[0].List6[0].Lia[0].Ch20[0]",
      "FieldNameAlt": "The trial has been set for",
      "FieldFlags": "0",
      "FieldValue": "",
      "FieldJustification": "Left"
    },
    {
      "FieldType": "Text",
      "FieldName": "CM-110[0].Page2[0].List6[0].Lia[0].Date7[0]",
      "FieldNameAlt": "date",
      "FieldFlags": "8388608",
      "FieldValue": "",
      "FieldJustification": "Left"
    },
    {
      "FieldType": "Button",
      "FieldName": "CM-110[0].Page2[0].List6[0].Lib[0].Ch20[0]",
      "FieldNameAlt": "No trial date has been set. This case will be ready for trial within 12 months of the date of the filing of the complaint.",
      "FieldFlags": "0",
      "FieldValue": "",
      "FieldJustification": "Left"
    },
    {
      "FieldType": "Text",
      "FieldName": "CM-110[0].Page2[0].List6[0].Lib[0].FillText8[0]",
      "FieldNameAlt": "IF not, explain",
      "FieldFlags": "8388608",
      "FieldValue": "",
      "FieldJustification": "Left"
    },
    {
      "FieldType": "Text",
      "FieldName": "CM-110[0].Page2[0].List6[0].Lic[0].FillText12[0]",
      "FieldNameAlt": "Dates on which parties or attorneys will not be available for trial (specify dates and explain reasons for unavailability):",
      "FieldFlags": "8392704",
      "FieldValue": "",
      "FieldJustification": "Left"
    },
    {
      "FieldType": "Button",
      "FieldName": "CM-110[0].Page2[0].List7[0].Lia[0].estimation1[0]",
      "FieldNameAlt": "days",
      "FieldFlags": "0",
      "FieldValue": "",
      "FieldJustification": "Left"
    },
    {
      "FieldType": "Text",
      "FieldName": "CM-110[0].Page2[0].List7[0].Lia[0].specify[0]",
      "FieldNameAlt": "specify number",
      "FieldFlags": "8388608",
      "FieldValue": "",
      "FieldJustification": "Left"
    },
    {
      "FieldType": "Button",
      "FieldName": "CM-110[0].Page2[0].List7[0].Lib[0].estimation1[0]",
      "FieldNameAlt": "hours (short causes)",
      "FieldFlags": "0",
      "FieldValue": "",
      "FieldJustification": "Left"
    },
    {
      "FieldType": "Text",
      "FieldName": "CM-110[0].Page2[0].List7[0].Lib[0].specify2[0]",
      "FieldNameAlt": "specify",
      "FieldFlags": "8388608",
      "FieldValue": "",
      "FieldJustification": "Left"
    },
    {
      "FieldType": "Button",
      "FieldName": "CM-110[0].Page2[0].List8[0].Ch25[0]",
      "FieldNameAlt": "by the attorney or party listed in the caption",
      "FieldFlags": "0",
      "FieldValue": "",
      "FieldJustification": "Left"
    },
    {
      "FieldType": "Button",
      "FieldName": "CM-110[0].Page2[0].List8[0].Ch26[0]",
      "FieldNameAlt": "by the following:",
      "FieldFlags": "0",
      "FieldValue": "",
      "FieldJustification": "Left"
    },
    {
      "FieldType": "Text",
      "FieldName": "CM-110[0].Page2[0].List8[0].Lia[0].FillText20[0]",
      "FieldNameAlt": "Attorney",
      "FieldFlags": "8388608",
      "FieldValue": "",
      "FieldJustification": "Left"
    },
    {
      "FieldType": "Text",
      "FieldName": "CM-110[0].Page2[0].List8[0].Lib[0].FillText21[0]",
      "FieldNameAlt": "Firm",
      "FieldFlags": "8388608",
      "FieldValue": "",
      "FieldJustification": "Left"
    },
    {
      "FieldType": "Text",
      "FieldName": "CM-110[0].Page2[0].List8[0].Lic[0].FillText22[0]",
      "FieldNameAlt": "Address",
      "FieldFlags": "8388608",
      "FieldValue": "",
      "FieldJustification": "Left"
    },
    {
      "FieldType": "Text",
      "FieldName": "CM-110[0].Page2[0].List8[0].Lid[0].FillText23[0]",
      "FieldNameAlt": "Telephone number",
      "FieldFlags": "8388608",
      "FieldValue": "",
      "FieldJustification": "Left"
    },
    {
      "FieldType": "Text",
      "FieldName": "CM-110[0].Page2[0].List8[0].Lie[0].TextField24[0]",
      "FieldNameAlt": "EMail address",
      "FieldFlags": "8388608",
      "FieldValue": "",
      "FieldJustification": "Left"
    },
    {
      "FieldType": "Text",
      "FieldName": "CM-110[0].Page2[0].List8[0].Lif[0].FillText25[0]",
      "FieldNameAlt": "Fax number",
      "FieldFlags": "8388608",
      "FieldValue": "",
      "FieldJustification": "Left"
    },
    {
      "FieldType": "Text",
      "FieldName": "CM-110[0].Page2[0].List8[0].Lig[0].FillText26[0]",
      "FieldNameAlt": "Party represented",
      "FieldFlags": "8388608",
      "FieldValue": "",
      "FieldJustification": "Left"
    },
    {
      "FieldType": "Button",
      "FieldName": "CM-110[0].Page2[0].List8[0].att[0]",
      "FieldNameAlt": "Additional representation is described in Attachment 8.",
      "FieldFlags": "0",
      "FieldValue": "",
      "FieldJustification": "Left"
    },
    {
      "FieldType": "Button",
      "FieldName": "CM-110[0].Page2[0].List9[0].item9[0].casew[0]",
      "FieldNameAlt": "Additional representation is described in Attachment 8.",
      "FieldFlags": "0",
      "FieldValue": "",
      "FieldJustification": "Left"
    },
    {
      "FieldType": "Text",
      "FieldName": "CM-110[0].Page2[0].List9[0].item9[0].section[0]",
      "FieldNameAlt": "Specify code section",
      "FieldFlags": "8388608",
      "FieldValue": "",
      "FieldJustification": "Left"
    },
    {
      "FieldType": "Button",
      "FieldName": "CM-110[0].Page2[0].List10[0].Lia[0].SubLista[0].Lii1[0].counsel1[0]",
      "FieldNameAlt": "has",
      "FieldFlags": "0",
      "FieldValue": "",
      "FieldJustification": "Left"
    },
    {
      "FieldType": "Button",
      "FieldName": "CM-110[0].Page2[0].List10[0].Lia[0].SubLista[0].Lii1[0].counsel1[1]",
      "FieldNameAlt": "has not",
      "FieldFlags": "0",
      "FieldValue": "",
      "FieldJustification": "Left"
    },
    {
      "FieldType": "Button",
      "FieldName": "CM-110[0].Page2[0].List10[0].Lia[0].SubLista[0].Lii2[0].partya1[0]",
      "FieldNameAlt": "has",
      "FieldFlags": "0",
      "FieldValue": "",
      "FieldJustification": "Left"
    },
    {
      "FieldType": "Button",
      "FieldName": "CM-110[0].Page2[0].List10[0].Lia[0].SubLista[0].Lii2[0].partya1[1]",
      "FieldNameAlt": "has not",
      "FieldFlags": "0",
      "FieldValue": "",
      "FieldJustification": "Left"
    },
    {
      "FieldType": "Button",
      "FieldName": "CM-110[0].Page2[0].List10[0].Lib[0].SubListb[0].Lii1[0].arbitration[0]",
      "FieldNameAlt": "This matter is subject to mandatory judicial arbitration under Code of Civil Procedure section 1141.11 or to civil action mediation under Code of Civil Procedure section 1775.3 because the amount in controversy does not exceed the statutory limit.",
      "FieldFlags": "0",
      "FieldValue": "",
      "FieldJustification": "Left"
    },
    {
      "FieldType": "Button",
      "FieldName": "CM-110[0].Page2[0].List10[0].Lib[0].SubListb[0].Lii2[0].CheckBox03[0]",
      "FieldNameAlt": "Plaintiff elects to refer this case to judicial arbitration and agrees to limit recovery to the amount specified in Code of\rCivil Procedure section 1141.11.",
      "FieldFlags": "0",
      "FieldValue": "",
      "FieldJustification": "Left"
    },
    {
      "FieldType": "Button",
      "FieldName": "CM-110[0].Page2[0].List10[0].Lib[0].SubListb[0].Lii3[0].CheckBox04[0]",
      "FieldNameAlt": "This case is exempt from judicial arbitration under rule 3.811 of the California Rules of Court or from civil action  mediation under Code of Civil Procedure section 1775 et seq. ",
      "FieldFlags": "0",
      "FieldValue": "",
      "FieldJustification": "Left"
    },
    {
      "FieldType": "Text",
      "FieldName": "CM-110[0].Page2[0].List10[0].Lib[0].SubListb[0].Lii3[0].FillText18[0]",
      "FieldNameAlt": "specify exemption",
      "FieldFlags": "8388608",
      "FieldValue": "",
      "FieldJustification": "Left"
    },
    {
      "FieldType": "Text",
      "FieldName": "CM-110[0].Page3[0].PxCaption[0].TitlePartyName[0].Party1[0]",
      "FieldNameAlt": "PLAINTIFF or PETITIONER:",
      "FieldFlags": "8388609",
      "FieldValue": "",
      "FieldJustification": "Left"
    },
    {
      "FieldType": "Text",
      "FieldName": "CM-110[0].Page3[0].PxCaption[0].TitlePartyName[0].Party2[0]",
      "FieldNameAlt": "DEFENDANT or RESPONDENT:",
      "FieldFlags": "8388609",
      "FieldValue": "",
      "FieldJustification": "Left"
    },
    {
      "FieldType": "Text",
      "FieldName": "CM-110[0].Page3[0].PxCaption[0].CaseNumber[0].caseNumber[0]",
      "FieldNameAlt": "Case number",
      "FieldFlags": "8388609",
      "FieldValue": "",
      "FieldJustification": "Left"
    },
    {
      "FieldType": "Button",
      "FieldName": "CM-110[0].Page3[0].List10[0].Lic[0].Table1[0].Row1[0].sub1[0].limitedch[0]",
      "FieldNameAlt": "check here if The party or parties completing this form are willing to participate in the following ADR processes: Mediation",
      "FieldFlags": "0",
      "FieldValue": "",
      "FieldJustification": "Left"
    },
    {
      "FieldType": "Button",
      "FieldName": "CM-110[0].Page3[0].List10[0].Lic[0].Table1[0].Row1[0].sub2[0].partystatement10[0]",
      "FieldNameAlt": "Mediation session not yet scheduled",
      "FieldFlags": "0",
      "FieldValue": "",
      "FieldJustification": "Left"
    },
    {
      "FieldType": "Button",
      "FieldName": "CM-110[0].Page3[0].List10[0].Lic[0].Table1[0].Row1[0].sub2[0].partystatement2[0]",
      "FieldNameAlt": "Mediation session scheduled for",
      "FieldFlags": "0",
      "FieldValue": "",
      "FieldJustification": "Left"
    },
    {
      "FieldType": "Text",
      "FieldName": "CM-110[0].Page3[0].List10[0].Lic[0].Table1[0].Row1[0].sub2[0].DateField2[0]",
      "FieldNameAlt": "date",
      "FieldFlags": "8388608",
      "FieldValue": "",
      "FieldJustification": "Left"
    },
    {
      "FieldType": "Button",
      "FieldName": "CM-110[0].Page3[0].List10[0].Lic[0].Table1[0].Row1[0].sub2[0].partystatement3[0]",
      "FieldNameAlt": "Agreed to complete mediation by",
      "FieldFlags": "0",
      "FieldValue": "",
      "FieldJustification": "Left"
    },
    {
      "FieldType": "Text",
      "FieldName": "CM-110[0].Page3[0].List10[0].Lic[0].Table1[0].Row1[0].sub2[0].DateField3[0]",
      "FieldNameAlt": "date",
      "FieldFlags": "8388608",
      "FieldValue": "",
      "FieldJustification": "Left"
    },
    {
      "FieldType": "Button",
      "FieldName": "CM-110[0].Page3[0].List10[0].Lic[0].Table1[0].Row1[0].sub2[0].partystatement4[0]",
      "FieldNameAlt": "Mediation completed on",
      "FieldFlags": "0",
      "FieldValue": "",
      "FieldJustification": "Left"
    },
    {
      "FieldType": "Text",
      "FieldName": "CM-110[0].Page3[0].List10[0].Lic[0].Table1[0].Row1[0].sub2[0].DateField4[0]",
      "FieldNameAlt": "date",
      "FieldFlags": "8388608",
      "FieldValue": "",
      "FieldJustification": "Left"
    },
    {
      "FieldType": "Button",
      "FieldName": "CM-110[0].Page3[0].List10[0].Lic[0].Table1[0].Row2[0].sub3[0].limitedch1[0]",
      "FieldNameAlt": "check here if The party or parties completing this form are willing to participate in the following ADR processes: Settlement conference",
      "FieldFlags": "0",
      "FieldValue": "",
      "FieldJustification": "Left"
    },
    {
      "FieldType": "Button",
      "FieldName": "CM-110[0].Page3[0].List10[0].Lic[0].Table1[0].Row2[0].sub4[0].partystatement5[0]",
      "FieldNameAlt": "Settlement conference not yet scheduled",
      "FieldFlags": "0",
      "FieldValue": "",
      "FieldJustification": "Left"
    },
    {
      "FieldType": "Button",
      "FieldName": "CM-110[0].Page3[0].List10[0].Lic[0].Table1[0].Row2[0].sub4[0].partystatement6[0]",
      "FieldNameAlt": "Settlement conference scheduled for",
      "FieldFlags": "0",
      "FieldValue": "",
      "FieldJustification": "Left"
    },
    {
      "FieldType": "Text",
      "FieldName": "CM-110[0].Page3[0].List10[0].Lic[0].Table1[0].Row2[0].sub4[0].DateField5[0]",
      "FieldNameAlt": "date",
      "FieldFlags": "8388608",
      "FieldValue": "",
      "FieldJustification": "Left"
    },
    {
      "FieldType": "Button",
      "FieldName": "CM-110[0].Page3[0].List10[0].Lic[0].Table1[0].Row2[0].sub4[0].partystatement7[0]",
      "FieldNameAlt": "Agreed to complete settlement conference by",
      "FieldFlags": "0",
      "FieldValue": "",
      "FieldJustification": "Left"
    },
    {
      "FieldType": "Text",
      "FieldName": "CM-110[0].Page3[0].List10[0].Lic[0].Table1[0].Row2[0].sub4[0].DateField6[0]",
      "FieldNameAlt": "date",
      "FieldFlags": "8388608",
      "FieldValue": "",
      "FieldJustification": "Left"
    },
    {
      "FieldType": "Button",
      "FieldName": "CM-110[0].Page3[0].List10[0].Lic[0].Table1[0].Row2[0].sub4[0].partystatement8[0]",
      "FieldNameAlt": "Settlement conference completed on",
      "FieldFlags": "0",
      "FieldValue": "",
      "FieldJustification": "Left"
    },
    {
      "FieldType": "Text",
      "FieldName": "CM-110[0].Page3[0].List10[0].Lic[0].Table1[0].Row2[0].sub4[0].DateField7[0]",
      "FieldNameAlt": "date",
      "FieldFlags": "8388608",
      "FieldValue": "",
      "FieldJustification": "Left"
    },
    {
      "FieldType": "Button",
      "FieldName": "CM-110[0].Page3[0].List10[0].Lic[0].Table1[0].Row3[0].sub5[0].limitedch2[0]",
      "FieldNameAlt": "check here if The party or parties completing this form are willing to participate in the following ADR processes: Neutral evaluation",
      "FieldFlags": "0",
      "FieldValue": "",
      "FieldJustification": "Left"
    },
    {
      "FieldType": "Button",
      "FieldName": "CM-110[0].Page3[0].List10[0].Lic[0].Table1[0].Row3[0].sub6[0].partystatement9[0]",
      "FieldNameAlt": "Neutral evaluation not yet scheduled",
      "FieldFlags": "0",
      "FieldValue": "",
      "FieldJustification": "Left"
    },
    {
      "FieldType": "Button",
      "FieldName": "CM-110[0].Page3[0].List10[0].Lic[0].Table1[0].Row3[0].sub6[0].partystatement10[0]",
      "FieldNameAlt": "Neutral evaluation scheduled for",
      "FieldFlags": "0",
      "FieldValue": "",
      "FieldJustification": "Left"
    },
    {
      "FieldType": "Text",
      "FieldName": "CM-110[0].Page3[0].List10[0].Lic[0].Table1[0].Row3[0].sub6[0].DateField8[0]",
      "FieldNameAlt": "date",
      "FieldFlags": "8388608",
      "FieldValue": "",
      "FieldJustification": "Left"
    },
    {
      "FieldType": "Button",
      "FieldName": "CM-110[0].Page3[0].List10[0].Lic[0].Table1[0].Row3[0].sub6[0].partystatement11[0]",
      "FieldNameAlt": "Agreed to complete neutral evaluation by",
      "FieldFlags": "0",
      "FieldValue": "",
      "FieldJustification": "Left"
    },
    {
      "FieldType": "Text",
      "FieldName": "CM-110[0].Page3[0].List10[0].Lic[0].Table1[0].Row3[0].sub6[0].DateField9[0]",
      "FieldNameAlt": "date",
      "FieldFlags": "8388608",
      "FieldValue": "",
      "FieldJustification": "Left"
    },
    {
      "FieldType": "Button",
      "FieldName": "CM-110[0].Page3[0].List10[0].Lic[0].Table1[0].Row3[0].sub6[0].partystatement12[0]",
      "FieldNameAlt": "Neutral evaluation completed on",
      "FieldFlags": "0",
      "FieldValue": "",
      "FieldJustification": "Left"
    },
    {
      "FieldType": "Text",
      "FieldName": "CM-110[0].Page3[0].List10[0].Lic[0].Table1[0].Row3[0].sub6[0].DateField10[0]",
      "FieldNameAlt": "date",
      "FieldFlags": "8388608",
      "FieldValue": "",
      "FieldJustification": "Left"
    },
    {
      "FieldType": "Button",
      "FieldName": "CM-110[0].Page3[0].List10[0].Lic[0].Table1[0].Row4[0].sub7[0].limitedch3[0]",
      "FieldNameAlt": "check here if The party or parties completing this form are willing to participate in the following ADR processes: Non binding judicial arbitration",
      "FieldFlags": "0",
      "FieldValue": "",
      "FieldJustification": "Left"
    },
    {
      "FieldType": "Button",
      "FieldName": "CM-110[0].Page3[0].List10[0].Lic[0].Table1[0].Row4[0].sub8[0].partystatement13[0]",
      "FieldNameAlt": "Judicial arbitration not yet scheduled",
      "FieldFlags": "0",
      "FieldValue": "",
      "FieldJustification": "Left"
    },
    {
      "FieldType": "Button",
      "FieldName": "CM-110[0].Page3[0].List10[0].Lic[0].Table1[0].Row4[0].sub8[0].partystatement14[0]",
      "FieldNameAlt": "Judicial arbitration scheduled for",
      "FieldFlags": "0",
      "FieldValue": "",
      "FieldJustification": "Left"
    },
    {
      "FieldType": "Text",
      "FieldName": "CM-110[0].Page3[0].List10[0].Lic[0].Table1[0].Row4[0].sub8[0].DateField11[0]",
      "FieldNameAlt": "date",
      "FieldFlags": "8388608",
      "FieldValue": "",
      "FieldJustification": "Left"
    },
    {
      "FieldType": "Button",
      "FieldName": "CM-110[0].Page3[0].List10[0].Lic[0].Table1[0].Row4[0].sub8[0].partystatement15[0]",
      "FieldNameAlt": "Agreed to complete judicial arbitration by",
      "FieldFlags": "0",
      "FieldValue": "",
      "FieldJustification": "Left"
    },
    {
      "FieldType": "Text",
      "FieldName": "CM-110[0].Page3[0].List10[0].Lic[0].Table1[0].Row4[0].sub8[0].DateField12[0]",
      "FieldNameAlt": "date",
      "FieldFlags": "8388608",
      "FieldValue": "",
      "FieldJustification": "Left"
    },
    {
      "FieldType": "Button",
      "FieldName": "CM-110[0].Page3[0].List10[0].Lic[0].Table1[0].Row4[0].sub8[0].partystatement16[0]",
      "FieldNameAlt": "Judicial arbitration completed on",
      "FieldFlags": "0",
      "FieldValue": "",
      "FieldJustification": "Left"
    },
    {
      "FieldType": "Text",
      "FieldName": "CM-110[0].Page3[0].List10[0].Lic[0].Table1[0].Row4[0].sub8[0].DateField13[0]",
      "FieldNameAlt": "date",
      "FieldFlags": "8388608",
      "FieldValue": "",
      "FieldJustification": "Left"
    },
    {
      "FieldType": "Button",
      "FieldName": "CM-110[0].Page3[0].List10[0].Lic[0].Table1[0].Row5[0].sub9[0].limitedch4[0]",
      "FieldNameAlt": "check here if The party or parties completing this form are willing to participate in the following ADR processes: Binding private arbitration",
      "FieldFlags": "0",
      "FieldValue": "",
      "FieldJustification": "Left"
    },
    {
      "FieldType": "Button",
      "FieldName": "CM-110[0].Page3[0].List10[0].Lic[0].Table1[0].Row5[0].sub10[0].partystatement17[0]",
      "FieldNameAlt": "Private arbitration not yet scheduled",
      "FieldFlags": "0",
      "FieldValue": "",
      "FieldJustification": "Left"
    },
    {
      "FieldType": "Button",
      "FieldName": "CM-110[0].Page3[0].List10[0].Lic[0].Table1[0].Row5[0].sub10[0].partystatement18[0]",
      "FieldNameAlt": "Private arbitration scheduled for",
      "FieldFlags": "0",
      "FieldValue": "",
      "FieldJustification": "Left"
    },
    {
      "FieldType": "Text",
      "FieldName": "CM-110[0].Page3[0].List10[0].Lic[0].Table1[0].Row5[0].sub10[0].DateField14[0]",
      "FieldNameAlt": "date",
      "FieldFlags": "8388608",
      "FieldValue": "",
      "FieldJustification": "Left"
    },
    {
      "FieldType": "Button",
      "FieldName": "CM-110[0].Page3[0].List10[0].Lic[0].Table1[0].Row5[0].sub10[0].partystatement19[0]",
      "FieldNameAlt": "Agreed to complete private arbitration by",
      "FieldFlags": "0",
      "FieldValue": "",
      "FieldJustification": "Left"
    },
    {
      "FieldType": "Text",
      "FieldName": "CM-110[0].Page3[0].List10[0].Lic[0].Table1[0].Row5[0].sub10[0].DateField15[0]",
      "FieldNameAlt": "date",
      "FieldFlags": "8388608",
      "FieldValue": "",
      "FieldJustification": "Left"
    },
    {
      "FieldType": "Button",
      "FieldName": "CM-110[0].Page3[0].List10[0].Lic[0].Table1[0].Row5[0].sub10[0].partystatement20[0]",
      "FieldNameAlt": "Private arbitration completed on",
      "FieldFlags": "0",
      "FieldValue": "",
      "FieldJustification": "Left"
    },
    {
      "FieldType": "Text",
      "FieldName": "CM-110[0].Page3[0].List10[0].Lic[0].Table1[0].Row5[0].sub10[0].DateField16[0]",
      "FieldNameAlt": "date",
      "FieldFlags": "8388608",
      "FieldValue": "",
      "FieldJustification": "Left"
    },
    {
      "FieldType": "Button",
      "FieldName": "CM-110[0].Page3[0].List10[0].Lic[0].Table1[0].Row6[0].sub11[0].limitedch5[0]",
      "FieldNameAlt": "check here if the party or parties completing this form are willing to participate in the following ADR processes: Other",
      "FieldFlags": "0",
      "FieldValue": "",
      "FieldJustification": "Left"
    },
    {
      "FieldType": "Button",
      "FieldName": "CM-110[0].Page3[0].List10[0].Lic[0].Table1[0].Row6[0].sub12[0].partystatement21[0]",
      "FieldNameAlt": "ADR session not yet scheduled",
      "FieldFlags": "0",
      "FieldValue": "",
      "FieldJustification": "Left"
    },
    {
      "FieldType": "Button",
      "FieldName": "CM-110[0].Page3[0].List10[0].Lic[0].Table1[0].Row6[0].sub12[0].partystatement22[0]",
      "FieldNameAlt": "ADR session scheduled for",
      "FieldFlags": "0",
      "FieldValue": "",
      "FieldJustification": "Left"
    },
    {
      "FieldType": "Text",
      "FieldName": "CM-110[0].Page3[0].List10[0].Lic[0].Table1[0].Row6[0].sub12[0].DateField17[0]",
      "FieldNameAlt": "date",
      "FieldFlags": "8388608",
      "FieldValue": "",
      "FieldJustification": "Left"
    },
    {
      "FieldType": "Button",
      "FieldName": "CM-110[0].Page3[0].List10[0].Lic[0].Table1[0].Row6[0].sub12[0].partystatement23[0]",
      "FieldNameAlt": "Agreed to complete ADR session by",
      "FieldFlags": "0",
      "FieldValue": "",
      "FieldJustification": "Left"
    },
    {
      "FieldType": "Text",
      "FieldName": "CM-110[0].Page3[0].List10[0].Lic[0].Table1[0].Row6[0].sub12[0].DateField18[0]",
      "FieldNameAlt": "date",
      "FieldFlags": "8388608",
      "FieldValue": "",
      "FieldJustification": "Left"
    },
    {
      "FieldType": "Button",
      "FieldName": "CM-110[0].Page3[0].List10[0].Lic[0].Table1[0].Row6[0].sub12[0].partystatement19[0]",
      "FieldNameAlt": "ADR completed on",
      "FieldFlags": "0",
      "FieldValue": "",
      "FieldJustification": "Left"
    },
    {
      "FieldType": "Text",
      "FieldName": "CM-110[0].Page3[0].List10[0].Lic[0].Table1[0].Row6[0].sub12[0].DateField19[0]",
      "FieldNameAlt": "date",
      "FieldFlags": "8388608",
      "FieldValue": "",
      "FieldJustification": "Left"
    },
    {
      "FieldType": "Text",
      "FieldName": "CM-110[0].Page4[0].PxCaption[0].TitlePartyName[0].Party1[0]",
      "FieldNameAlt": "PLAINTIFF or PETITIONER:",
      "FieldFlags": "8388609",
      "FieldValue": "",
      "FieldJustification": "Left"
    },
    {
      "FieldType": "Text",
      "FieldName": "CM-110[0].Page4[0].PxCaption[0].TitlePartyName[0].Party2[0]",
      "FieldNameAlt": "DEFENDANT or RESPONDENT:",
      "FieldFlags": "8388609",
      "FieldValue": "",
      "FieldJustification": "Left"
    },
    {
      "FieldType": "Text",
      "FieldName": "CM-110[0].Page4[0].PxCaption[0].CaseNumber[0].caseNumber[0]",
      "FieldNameAlt": "Case number",
      "FieldFlags": "8388609",
      "FieldValue": "",
      "FieldJustification": "Left"
    },
    {
      "FieldType": "Button",
      "FieldName": "CM-110[0].Page4[0].List11[0].Lia[0].Ch31[0]",
      "FieldNameAlt": "Insurance carrier, if any, for party filing this statement",
      "FieldFlags": "0",
      "FieldValue": "",
      "FieldJustification": "Left"
    },
    {
      "FieldType": "Text",
      "FieldName": "CM-110[0].Page4[0].List11[0].Lia[0].Name1[0]",
      "FieldNameAlt": "name",
      "FieldFlags": "8388608",
      "FieldValue": "",
      "FieldJustification": "Left"
    },
    {
      "FieldType": "Button",
      "FieldName": "CM-110[0].Page4[0].List11[0].Lib[0].Yes10[0]",
      "FieldNameAlt": "yes",
      "FieldFlags": "0",
      "FieldValue": "",
      "FieldJustification": "Left"
    },
    {
      "FieldType": "Button",
      "FieldName": "CM-110[0].Page4[0].List11[0].Lib[0].Yes10[1]",
      "FieldNameAlt": "No",
      "FieldFlags": "0",
      "FieldValue": "",
      "FieldJustification": "Left"
    },
    {
      "FieldType": "Button",
      "FieldName": "CM-110[0].Page4[0].List11[0].Lic[0].Ch32[0]",
      "FieldNameAlt": "Coverage issues will significantly affect resolution of this case",
      "FieldFlags": "0",
      "FieldValue": "",
      "FieldJustification": "Left"
    },
    {
      "FieldType": "Text",
      "FieldName": "CM-110[0].Page4[0].List11[0].Lic[0].Field1[0]",
      "FieldNameAlt": "Explain",
      "FieldFlags": "8392704",
      "FieldValue": "",
      "FieldJustification": "Left"
    },
    {
      "FieldType": "Button",
      "FieldName": "CM-110[0].Page4[0].List12[0].item12[0].counsel15[0]",
      "FieldNameAlt": "Bankruptcy",
      "FieldFlags": "0",
      "FieldValue": "",
      "FieldJustification": "Left"
    },
    {
      "FieldType": "Button",
      "FieldName": "CM-110[0].Page4[0].List12[0].item12[0].counsel15[1]",
      "FieldNameAlt": "Other",
      "FieldFlags": "0",
      "FieldValue": "",
      "FieldJustification": "Left"
    },
    {
      "FieldType": "Text",
      "FieldName": "CM-110[0].Page4[0].List12[0].item12[0].specify12[0]",
      "FieldNameAlt": "Specify",
      "FieldFlags": "8388608",
      "FieldValue": "",
      "FieldJustification": "Left"
    },
    {
      "FieldType": "Text",
      "FieldName": "CM-110[0].Page4[0].List12[0].item12[0].Status[0]",
      "FieldNameAlt": "Status",
      "FieldFlags": "8388608",
      "FieldValue": "",
      "FieldJustification": "Left"
    },
    {
      "FieldType": "Button",
      "FieldName": "CM-110[0].Page4[0].List13[0].Lia[0].Ch35[0]",
      "FieldNameAlt": "There are companion, underlying, or related cases.",
      "FieldFlags": "0",
      "FieldValue": "",
      "FieldJustification": "Left"
    },
    {
      "FieldType": "Text",
      "FieldName": "CM-110[0].Page4[0].List13[0].Lia[0].SubLista[0].Lii1[0].Field2[0]",
      "FieldNameAlt": "Name of case:",
      "FieldFlags": "8388608",
      "FieldValue": "",
      "FieldJustification": "Left"
    },
    {
      "FieldType": "Text",
      "FieldName": "CM-110[0].Page4[0].List13[0].Lia[0].SubLista[0].Lii2[0].Field3[0]",
      "FieldNameAlt": "Name of court:",
      "FieldFlags": "8388608",
      "FieldValue": "",
      "FieldJustification": "Left"
    },
    {
      "FieldType": "Text",
      "FieldName": "CM-110[0].Page4[0].List13[0].Lia[0].SubLista[0].Lii3[0].Field4[0]",
      "FieldNameAlt": "Case number:",
      "FieldFlags": "8388608",
      "FieldValue": "",
      "FieldJustification": "Left"
    },
    {
      "FieldType": "Text",
      "FieldName": "CM-110[0].Page4[0].List13[0].Lia[0].SubLista[0].Lii4[0].Field5[0]",
      "FieldNameAlt": "Status:",
      "FieldFlags": "8388608",
      "FieldValue": "",
      "FieldJustification": "Left"
    },
    {
      "FieldType": "Button",
      "FieldName": "CM-110[0].Page4[0].List13[0].Lia[0].limitedatt11[0]",
      "FieldNameAlt": "Additional cases are described in Attachment 13a.",
      "FieldFlags": "0",
      "FieldValue": "",
      "FieldJustification": "Left"
    },
    {
      "FieldType": "Text",
      "FieldName": "CM-110[0].Page4[0].List13[0].Lib[0].Field6[0]",
      "FieldNameAlt": "will be filed by (name party)",
      "FieldFlags": "8388608",
      "FieldValue": "",
      "FieldJustification": "Left"
    },
    {
      "FieldType": "Button",
      "FieldName": "CM-110[0].Page4[0].List13[0].Lib[0].RB2Choices12[0]",
      "FieldNameAlt": "A motion to",
      "FieldFlags": "0",
      "FieldValue": "",
      "FieldJustification": "Left"
    },
    {
      "FieldType": "Button",
      "FieldName": "CM-110[0].Page4[0].List13[0].Lib[0].RB2Choices13[0]",
      "FieldNameAlt": "consolidate",
      "FieldFlags": "0",
      "FieldValue": "",
      "FieldJustification": "Left"
    },
    {
      "FieldType": "Button",
      "FieldName": "CM-110[0].Page4[0].List13[0].Lib[0].RB2Choices13[1]",
      "FieldNameAlt": "coordinate",
      "FieldFlags": "0",
      "FieldValue": "",
      "FieldJustification": "Left"
    },
    {
      "FieldType": "Button",
      "FieldName": "CM-110[0].Page4[0].List14[0].item14[0].Ch37[0]",
      "FieldNameAlt": "The party or parties intend to file a motion for an order bifurcating, severing, or coordinating the following issues or causes of action",
      "FieldFlags": "0",
      "FieldValue": "",
      "FieldJustification": "Left"
    },
    {
      "FieldType": "Text",
      "FieldName": "CM-110[0].Page4[0].List14[0].item14[0].Field7[0]",
      "FieldNameAlt": "specify moving party, type of motion, and reasons",
      "FieldFlags": "8392704",
      "FieldValue": "",
      "FieldJustification": "Left"
    },
    {
      "FieldType": "Button",
      "FieldName": "CM-110[0].Page4[0].List15[0].item15[0].Ch39[0]",
      "FieldNameAlt": "The party or parties expect to file the following motions before trial",
      "FieldFlags": "0",
      "FieldValue": "",
      "FieldJustification": "Left"
    },
    {
      "FieldType": "Text",
      "FieldName": "CM-110[0].Page4[0].List15[0].item15[0].Field16[0]",
      "FieldNameAlt": "Specify moving party, type of motion and issues",
      "FieldFlags": "8392704",
      "FieldValue": "",
      "FieldJustification": "Left"
    },
    {
      "FieldType": "Button",
      "FieldName": "CM-110[0].Page4[0].List16[0].Lia[0].disco[0]",
      "FieldNameAlt": "The party or parties have completed all discovery.",
      "FieldFlags": "0",
      "FieldValue": "",
      "FieldJustification": "Left"
    },
    {
      "FieldType": "Button",
      "FieldName": "CM-110[0].Page4[0].List16[0].Lib[0].disco1[0]",
      "FieldNameAlt": "The following discovery will be completed by the date specified (describe all anticipated discovery):",
      "FieldFlags": "0",
      "FieldValue": "",
      "FieldJustification": "Left"
    },
    {
      "FieldType": "Text",
      "FieldName": "CM-110[0].Page4[0].List16[0].Lib[0].Table[0].AdmProceedingTitle_ft1[0]",
      "FieldNameAlt": "Enter Party field 1",
      "FieldFlags": "8388608",
      "FieldValue": "",
      "FieldJustification": "Left"
    },
    {
      "FieldType": "Text",
      "FieldName": "CM-110[0].Page4[0].List16[0].Lib[0].Table[0].AdmProceedingTitle_ft2[0]",
      "FieldNameAlt": "Enter Description field 1",
      "FieldFlags": "8388608",
      "FieldValue": "",
      "FieldJustification": "Left"
    },
    {
      "FieldType": "Text",
      "FieldName": "CM-110[0].Page4[0].List16[0].Lib[0].Table[0].AdmProceedingDate_ft3[0]",
      "FieldNameAlt": "Enter Date field 1",
      "FieldFlags": "8388608",
      "FieldValue": "",
      "FieldJustification": "Left"
    },
    {
      "FieldType": "Text",
      "FieldName": "CM-110[0].Page4[0].List16[0].Lib[0].Table[0].AdmProceedingTitle_ft4[0]",
      "FieldNameAlt": "Enter Party field 2",
      "FieldFlags": "8388608",
      "FieldValue": "",
      "FieldJustification": "Left"
    },
    {
      "FieldType": "Text",
      "FieldName": "CM-110[0].Page4[0].List16[0].Lib[0].Table[0].AdmProceedingTitle_ft5[0]",
      "FieldNameAlt": "Enter Description field 2",
      "FieldFlags": "8388608",
      "FieldValue": "",
      "FieldJustification": "Left"
    },
    {
      "FieldType": "Text",
      "FieldName": "CM-110[0].Page4[0].List16[0].Lib[0].Table[0].AdmProceedingDate_ft6[0]",
      "FieldNameAlt": "Enter Date field 2",
      "FieldFlags": "8388608",
      "FieldValue": "",
      "FieldJustification": "Left"
    },
    {
      "FieldType": "Text",
      "FieldName": "CM-110[0].Page4[0].List16[0].Lib[0].Table[0].AdmProceedingTitle_ft7[0]",
      "FieldNameAlt": "Enter Party field 3",
      "FieldFlags": "8388608",
      "FieldValue": "",
      "FieldJustification": "Left"
    },
    {
      "FieldType": "Text",
      "FieldName": "CM-110[0].Page4[0].List16[0].Lib[0].Table[0].AdmProceedingTitle_ft8[0]",
      "FieldNameAlt": "Enter Description field 3",
      "FieldFlags": "8388608",
      "FieldValue": "",
      "FieldJustification": "Left"
    },
    {
      "FieldType": "Text",
      "FieldName": "CM-110[0].Page4[0].List16[0].Lib[0].Table[0].AdmProceedingDate_ft9[0]",
      "FieldNameAlt": "Enter Date field 3",
      "FieldFlags": "8388608",
      "FieldValue": "",
      "FieldJustification": "Left"
    },
    {
      "FieldType": "Text",
      "FieldName": "CM-110[0].Page4[0].List16[0].Lib[0].Table[0].AdmProceedingTitle_ft10[0]",
      "FieldNameAlt": "Enter Party field 4",
      "FieldFlags": "8388608",
      "FieldValue": "",
      "FieldJustification": "Left"
    },
    {
      "FieldType": "Text",
      "FieldName": "CM-110[0].Page4[0].List16[0].Lib[0].Table[0].AdmProceedingTitle_ft11[0]",
      "FieldNameAlt": "Enter Description field 4",
      "FieldFlags": "8388608",
      "FieldValue": "",
      "FieldJustification": "Left"
    },
    {
      "FieldType": "Text",
      "FieldName": "CM-110[0].Page4[0].List16[0].Lib[0].Table[0].AdmProceedingDate_ft12[0]",
      "FieldNameAlt": "Enter Date field 4",
      "FieldFlags": "8388608",
      "FieldValue": "",
      "FieldJustification": "Left"
    },
    {
      "FieldType": "Text",
      "FieldName": "CM-110[0].Page4[0].List16[0].Lib[0].Table[0].AdmProceedingTitle_ft13[0]",
      "FieldNameAlt": "Enter Party field 5",
      "FieldFlags": "8388608",
      "FieldValue": "",
      "FieldJustification": "Left"
    },
    {
      "FieldType": "Text",
      "FieldName": "CM-110[0].Page4[0].List16[0].Lib[0].Table[0].AdmProceedingTitle_ft[0]",
      "FieldNameAlt": "Enter Description field 5",
      "FieldFlags": "8388608",
      "FieldValue": "",
      "FieldJustification": "Left"
    },
    {
      "FieldType": "Text",
      "FieldName": "CM-110[0].Page4[0].List16[0].Lib[0].Table[0].AdmProceedingDate_ft[0]",
      "FieldNameAlt": "Enter Date field 5",
      "FieldFlags": "8388608",
      "FieldValue": "",
      "FieldJustification": "Left"
    },
    {
      "FieldType": "Button",
      "FieldName": "CM-110[0].Page4[0].List16[0].Lic[0].Ch40[0]",
      "FieldNameAlt": "The following discovery issues, including issues regarding the discovery of electronically stored information, are anticipated",
      "FieldFlags": "0",
      "FieldValue": "",
      "FieldJustification": "Left"
    },
    {
      "FieldType": "Text",
      "FieldName": "CM-110[0].Page4[0].List16[0].Lic[0].Field21[0]",
      "FieldNameAlt": "specify",
      "FieldFlags": "8392704",
      "FieldValue": "",
      "FieldJustification": "Left"
    },
    {
      "FieldType": "Button",
      "FieldName": "CM-110[0].#pageSet[0].MPLast[0].FooterButtons[0].Print[0]",
      "FieldNameAlt": "Print this form",
      "FieldFlags": "65536",
      "FieldValue": "",
      "FieldJustification": "Left"
    },
    {
      "FieldType": "Button",
      "FieldName": "CM-110[0].#pageSet[0].MPLast[0].FooterButtons[0].Save[0]",
      "FieldNameAlt": "Save this form",
      "FieldFlags": "65536",
      "FieldValue": "",
      "FieldJustification": "Left"
    },
    {
      "FieldType": "Button",
      "FieldName": "CM-110[0].#pageSet[0].MPLast[0].FooterButtons[0].Reset[0]",
      "FieldNameAlt": "Clear this form",
      "FieldFlags": "65536",
      "FieldValue": "",
      "FieldJustification": "Left"
    },
    {
      "FieldType": "Button",
      "FieldName": "CM-110[0].#pageSet[0].MPLast[0].FooterButtons[0].Warning[0]",
      "FieldNameAlt": "For your protection and privacy, please press the Clear This Form button after you have printed the form.",
      "FieldFlags": "65536",
      "FieldValue": "",
      "FieldJustification": "Left"
    },
    {
      "FieldType": "Text",
      "FieldName": "CM-110[0].Page5[0].PxCaption[0].TitlePartyName[0].Party1[0]",
      "FieldNameAlt": "PLAINTIFF or PETITIONER:",
      "FieldFlags": "8388609",
      "FieldValue": "",
      "FieldJustification": "Left"
    },
    {
      "FieldType": "Text",
      "FieldName": "CM-110[0].Page5[0].PxCaption[0].TitlePartyName[0].Party2[0]",
      "FieldNameAlt": "DEFENDANT or RESPONDENT:",
      "FieldFlags": "8388609",
      "FieldValue": "",
      "FieldJustification": "Left"
    },
    {
      "FieldType": "Text",
      "FieldName": "CM-110[0].Page5[0].PxCaption[0].CaseNumber[0].caseNumber[0]",
      "FieldNameAlt": "Case number",
      "FieldFlags": "8388609",
      "FieldValue": "",
      "FieldJustification": "Left"
    },
    {
      "FieldType": "Button",
      "FieldName": "CM-110[0].Page5[0].List17[0].Lia[0].estimation2[0]",
      "FieldNameAlt": "This is a limited civil case (i.e., the amount demanded is $35,000 or less) and the economic litigation procedures in Code\rof Civil Procedure sections 90-98 will apply to this case.",
      "FieldFlags": "0",
      "FieldValue": "",
      "FieldJustification": "Left"
    },
    {
      "FieldType": "Button",
      "FieldName": "CM-110[0].Page5[0].List17[0].Lib[0].estimation2[0]",
      "FieldNameAlt": "This is a limited civil case and a motion to withdraw the case from the economic litigation procedures or for additional\rdiscovery will be filed",
      "FieldFlags": "0",
      "FieldValue": "",
      "FieldJustification": "Left"
    },
    {
      "FieldType": "Text",
      "FieldName": "CM-110[0].Page5[0].List17[0].Lib[0].Field26[0]",
      "FieldNameAlt": "if checked, explain specifically why economic litigation procedures relating to discovery or trial should not apply to this case",
      "FieldFlags": "8392704",
      "FieldValue": "",
      "FieldJustification": "Left"
    },
    {
      "FieldType": "Button",
      "FieldName": "CM-110[0].Page5[0].List18[0].item18[0].Ch42[0]",
      "FieldNameAlt": "The party or parties request that the following additional matters be considered or determined at the case management\rconference",
      "FieldFlags": "0",
      "FieldValue": "",
      "FieldJustification": "Left"
    },
    {
      "FieldType": "Text",
      "FieldName": "CM-110[0].Page5[0].List18[0].item18[0].Field42[0]",
      "FieldNameAlt": "specify",
      "FieldFlags": "8392704",
      "FieldValue": "",
      "FieldJustification": "Left"
    },
    {
      "FieldType": "Button",
      "FieldName": "CM-110[0].Page5[0].List19[0].Lia[0].estimation3[0]",
      "FieldNameAlt": "The party or parties have met and conferred with all parties on all subjects required by rule 3.724 of the California Rules\rof Court",
      "FieldFlags": "0",
      "FieldValue": "",
      "FieldJustification": "Left"
    },
    {
      "FieldType": "Text",
      "FieldName": "CM-110[0].Page5[0].List19[0].Lia[0].Field43[0]",
      "FieldNameAlt": "if not, explain",
      "FieldFlags": "8392704",
      "FieldValue": "",
      "FieldJustification": "Left"
    },
    {
      "FieldType": "Button",
      "FieldName": "CM-110[0].Page5[0].List19[0].Lib[0].estimation3[0]",
      "FieldNameAlt": "After meeting and conferring as required by rule 3.724 of the California Rules of Court, the parties agree on the following",
      "FieldFlags": "0",
      "FieldValue": "",
      "FieldJustification": "Left"
    },
    {
      "FieldType": "Text",
      "FieldName": "CM-110[0].Page5[0].List19[0].Lib[0].FillText44[0]",
      "FieldNameAlt": "spcify",
      "FieldFlags": "8392704",
      "FieldValue": "",
      "FieldJustification": "Left"
    },
    {
      "FieldType": "Text",
      "FieldName": "CM-110[0].Page5[0].List20[0].NumberOfPages[0].Numbers[0]",
      "FieldNameAlt": "Total number of pages attached (if any):",
      "FieldFlags": "8388608",
      "FieldValue": "",
      "FieldJustification": "Left"
    },
    {
      "FieldType": "Text",
      "FieldName": "CM-110[0].Page5[0].Sign[0].SigDate1[0]",
      "FieldNameAlt": "Date",
      "FieldFlags": "8388608",
      "FieldValue": "",
      "FieldJustification": "Left"
    },
    {
      "FieldType": "Text",
      "FieldName": "CM-110[0].Page5[0].Sign[0].SigName1[0]",
      "FieldNameAlt": "Type or print name",
      "FieldFlags": "8388608",
      "FieldValue": "",
      "FieldJustification": "Left"
    },
    {
      "FieldType": "Text",
      "FieldName": "CM-110[0].Page5[0].Sign[0].SigName2[0]",
      "FieldNameAlt": "Type or print name",
      "FieldFlags": "8388608",
      "FieldValue": "",
      "FieldJustification": "Left"
    },
    {
      "FieldType": "Button",
      "FieldName": "CM-110[0].Page5[0].Sign[0].addsign24[0]",
      "FieldNameAlt": "Additional signatures are attached.",
      "FieldFlags": "0",
      "FieldValue": "",
      "FieldJustification": "Left"
    }
  ]
}